Workbook

Sheet Mode d'emploi
A1: Relecture du contenu V5 (bloc 2)
A2: Rien de ce tableur n'apparaît dans l'app tant que ce n'est pas validé : tout est importé « à valider ».
A4: Ce que tu remplis (cases jaunes)
A5: Validé | B5: oui / non / à revoir | C5: oui : l'exercice ou l'entraînement devient visible. non : il reste caché. à revoir : précise dans Commentaire.
A6: Vidéo OK | B6: oui / non | C6: non : je cherche une autre vidéo.
A7: Commentaire | B7: texte libre | C7: Ce qu'il faut changer (consigne, niveau, intensité, vidéo...).
A8: Exemple | B8: Validé = oui | C8: Vidéo OK = non ; Commentaire = « vidéo trop rapide, en trouver une plus pédagogique »
A10: Où en est la relecture | B10: Nombre
A11: Exercices au total | B11: =COUNTA(Exercices!A2:A147) -> 146
A12: Dont nouveaux | B12: =COUNTIF(Exercices!C2:C147,"Nouveau") -> 103
A13: Exercices validés | B13: =COUNTIF(Exercices!D2:D147,"oui") -> 0
A14: Exercices à revoir | B14: =COUNTIF(Exercices!D2:D147,"à revoir") -> 0
A15: Vidéos refusées | B15: =COUNTIF(Exercices!E2:E147,"non") -> 0
A16: Entraînements au total | B16: =COUNTA(Entraînements!A2:A76) -> 75
A17: Entraînements validés | B17: =COUNTIF(Entraînements!D2:D76,"oui") -> 0
A18: Exercices restant à relire | B18: =COUNTA(Exercices!A2:A147)-COUNTA(Exercices!D2:D147) -> 146
A20: Poids pour estimer les calories (kg) | B20: 60 | C20: Exemple : 60 kg. Change-le pour voir les calories des entraînements à ton poids.
A22: À savoir
A23: Un entraînement validé ne s'affiche que si tous ses exercices sont validés aussi.
A24: Les 43 exercices existants gardent leur nom, leurs consignes et leurs niveaux : seules les étiquettes, le tutoriel, la source et la vidéo sont nouveaux.
A25: Calories : MET x poids x durée (Compendium 2024). La colonne des entraînements prend 60 kg pour exemple ; l'app utilisera le poids du profil.
A26: Sources : free-exercise-db (base ouverte, domaine public), NHS, Harvard Health, Yoga Journal, Yogamatters et références scientifiques. Aucun texte n'est copié.
A27: Vidéos : liens YouTube trouvés en ligne, en français quand c'était possible. Je ne peux pas les regarder : c'est à toi de vérifier qu'elles montrent le bon mouvement.

Sheet Exercices
A1: Identifiant | B1: Nom | C1: Statut | D1: Validé | E1: Vidéo OK | F1: Commentaire | G1: Discipline | H1: Zones | I1: Objectifs | J1: Intensité (1 à 5) | K1: Sauts | L1: Matériel nécessaire | M1: Par défaut | N1: Niveaux | O1: Muscles principaux | P1: Muscles secondaires | Q1: MET (Compendium 2024) | R1: Consignes | S1: Précaution | T1: Respiration | U1: Erreurs fréquentes | V1: Sources | W1: Vidéo proposée
A2: squat | B2: Squat au poids du corps | C2: Nouveau | G2: renforcement | H2: jambes, fessiers | I2: renforcer, tonifier | J2: 2 | K2: non | L2: aucun | M2: 12 répétitions | N2: 1. Amplitude confortable (10 rép.) 2. Cuisses parallèles au sol (12 rép.) 3. Descente lente en 3 s (12 rép.) 4. Pause de 2 s en bas (15 rép.) | O2: Quadriceps, Grand fessier | P2: Ischio-jambiers, Adducteurs, Bas du dos (lombaires) | Q2: 3 (code 02056, Renforcement au poids du corps, général) | R2: Debout, pieds un peu plus écartés que les hanches, pointes légèrement ouvertes. Pousse les fesses en arrière et descends comme pour t'asseoir, poitrine ouverte. Remonte en poussant dans tout le pied, genoux dans l'axe des orteils. | S2: Descends seulement jusqu'où ton dos reste long et tes talons au sol. | T2: Inspire en descendant, expire en remontant. | U2: Genoux qui rentrent vers l'intérieur. Talons qui décollent. Dos qui s'arrondit en bas. | V2: free-exercise-db (domaine public), fiche Bodyweight Squat : https://github.com/yuhonas/free-exercise-db/blob/main/exercises/Bodyweight_Squat.json NHS, Strength exercises : https://www.nhs.uk/live-well/exercise/strength-and-flexibility-exercises/strength-exercises/ | W2: Comment faire des squats de la bonne façon au poids du corps ou avec charge (français) https://www.youtube.com/watch?v=EMfbjJWIllU
A3: squat_sumo | B3: Squat sumo | C3: Nouveau | G3: renforcement | H3: jambes, fessiers | I3: renforcer, tonifier | J3: 2 | K3: non | L3: aucun | M3: 12 répétitions | N3: 1. Amplitude confortable (10 rép.) 2. Cuisses parallèles au sol (12 rép.) 3. Pause de 2 s en bas (12 rép.) 4. Haltère tenu des deux mains (12 rép.) | O3: Adducteurs, Grand fessier, Quadriceps | P3: Ischio-jambiers | Q3: 3 (code 02056, Renforcement au poids du corps, général) | R3: Pieds bien plus écartés que les épaules, pointes tournées vers l'extérieur. Descends le bassin à la verticale, buste droit, genoux ouverts vers les pieds. Remonte en serrant les fessiers. | S3: Les genoux suivent toujours la direction des pointes de pied. | T3: Inspire en descendant, expire en remontant. | U3: Pencher le buste en avant. Laisser les genoux se refermer. | V3: free-exercise-db (domaine public), fiche Plie Dumbbell Squat : https://github.com/yuhonas/free-exercise-db/blob/main/exercises/Plie_Dumbbell_Squat.json | W3: Comment faire un squat sumo (français) https://www.youtube.com/watch?v=xnvkQeZ_XaE
A4: chaise_mur | B4: Chaise contre le mur | C4: Nouveau | G4: renforcement | H4: jambes | I4: renforcer, tonifier | J4: 3 | K4: non | L4: mur | M4: 30 s | N4: 1. Genoux peu fléchis (20 s) 2. Genoux peu fléchis (30 s) 3. Cuisses presque parallèles au sol (30 s) 4. Cuisses parallèles au sol (45 s) | O4: Quadriceps | P4: Grand fessier, Adducteurs | Q4: 3 (code 02056, Renforcement au poids du corps, général) | R4: Dos plaqué contre le mur, pieds à environ 50 cm du mur. Glisse vers le bas jusqu'à la hauteur choisie, genoux au-dessus des chevilles. Tiens la position, mains sur les cuisses ou bras croisés. | S4: Si une douleur apparaît dans le genou, remonte un peu. | T4: Respire calmement, sans bloquer. | U4: Genoux qui dépassent largement les orteils. Appuyer les mains sur les cuisses pour tricher. | V4: NHS, Strength exercises : https://www.nhs.uk/live-well/exercise/strength-and-flexibility-exercises/strength-exercises/ | W4: La chaise murale : endurance et cuisses sans matériel (tuto rapide) (français) https://www.youtube.com/watch?v=-NuqBMIgrcc
A5: fente_avant | B5: Fente avant | C5: Nouveau | G5: renforcement | H5: jambes, fessiers | I5: renforcer, tonifier | J5: 3 | K5: non | L5: aucun | M5: 10 répétitions | N5: 1. Fente sur place, petite amplitude (8 rép.) 2. Fente sur place (10 rép.) 3. Pas en avant puis retour (10 rép.) 4. Haltères en main (10 rép.) | O5: Quadriceps, Grand fessier | P5: Ischio-jambiers, Adducteurs | Q5: 3.8 (code 02022, Callisthénie modérée (pompes, fentes)) | R5: Debout, fais un grand pas en avant. Descends le genou arrière vers le sol, buste droit. Pousse sur le pied avant pour revenir. Alterne les jambes. | S5: Le genou avant reste au-dessus de la cheville. Tiens-toi à une chaise si l'équilibre est difficile. | T5: Inspire en descendant, expire en remontant. | U5: Pas trop court : le genou avant part loin devant. Buste penché vers l'avant. | V5: free-exercise-db (domaine public), fiche Bodyweight Walking Lunge : https://github.com/yuhonas/free-exercise-db/blob/main/exercises/Bodyweight_Walking_Lunge.json NHS, Strength exercises : https://www.nhs.uk/live-well/exercise/strength-and-flexibility-exercises/strength-exercises/ | W5: Comment faire les fentes : technique et erreurs à éviter (français) https://www.youtube.com/watch?v=HH9FQpjXw7A
A6: fente_arriere | B6: Fente arrière | C6: Nouveau | G6: renforcement | H6: jambes, fessiers | I6: renforcer, tonifier | J6: 2 | K6: non | L6: aucun | M6: 10 répétitions | N6: 1. Main sur une chaise, petite amplitude (8 rép.) 2. Sans appui (10 rép.) 3. Descente lente en 3 s (10 rép.) 4. Haltères en main (10 rép.) | O6: Grand fessier, Quadriceps | P6: Ischio-jambiers | Q6: 3.8 (code 02022, Callisthénie modérée (pompes, fentes)) | R6: Debout, recule un pied d'un grand pas. Fléchis les deux genoux, le genou arrière descend vers le sol. Reviens en poussant sur le talon avant. Alterne. | S6: Plus facile pour les genoux que la fente avant : bon choix pour commencer. | T6: Inspire en reculant, expire en revenant. | U6: Pieds sur la même ligne : on perd l'équilibre. Genou arrière qui tape le sol. | V6: free-exercise-db (domaine public), fiche Dumbbell Rear Lunge : https://github.com/yuhonas/free-exercise-db/blob/main/exercises/Dumbbell_Rear_Lunge.json | W6: Comment faire une fente arrière correctement ? (français) https://www.youtube.com/watch?v=Zz8DrsAUIZo
A7: fente_laterale | B7: Fente latérale | C7: Nouveau | G7: renforcement | H7: jambes, fessiers | I7: renforcer, tonifier, mobilite | J7: 2 | K7: non | L7: aucun | M7: 10 répétitions | N7: 1. Petite amplitude (8 rép.) 2. Amplitude complète (10 rép.) 3. Pause de 2 s en bas (10 rép.) | O7: Adducteurs, Quadriceps, Grand fessier | P7: Moyen fessier | Q7: 3.8 (code 02022, Callisthénie modérée (pompes, fentes)) | R7: Debout, pieds joints. Fais un grand pas sur le côté. Plie le genou de ce côté et pousse les fesses en arrière, l'autre jambe reste tendue. Reviens au centre en poussant sur le pied. Alterne. | S7: Les deux pieds restent à plat et pointent vers l'avant. | T7: Inspire en descendant, expire en revenant. | U7: Genou plié qui rentre vers l'intérieur. Dos arrondi. | V7: free-exercise-db (domaine public), fiche Barbell Side Split Squat : https://github.com/yuhonas/free-exercise-db/blob/main/exercises/Barbell_Side_Split_Squat.json | W7: Musculation des cuisses : fentes latérales (français) https://www.youtube.com/watch?v=3EvkUQHvFkI
A8: fente_bulgare | B8: Fente bulgare (pied arrière sur une chaise) | C8: Nouveau | G8: renforcement | H8: jambes, fessiers | I8: renforcer, tonifier | J8: 4 | K8: non | L8: chaise | M8: 8 répétitions | N8: 1. Petite amplitude, main au mur (6 rép.) 2. Amplitude complète (8 rép.) 3. Descente lente en 3 s (8 rép.) 4. Haltères en main (8 rép.) | O8: Quadriceps, Grand fessier | P8: Ischio-jambiers, Adducteurs, Moyen fessier | Q8: 3.8 (code 02022, Callisthénie modérée (pompes, fentes)) | R8: Dos à une chaise stable, pose le dessus du pied arrière sur l'assise. Descends à la verticale sur la jambe avant, buste légèrement penché. Remonte en poussant dans le talon avant. Fais toutes les répétitions, puis change. | S8: Chaise calée contre un mur pour qu'elle ne glisse pas. | T8: Inspire en descendant, expire en remontant. | U8: Pied avant trop près de la chaise. Pousser avec la jambe arrière. | V8: free-exercise-db (domaine public), fiche Split Squats : https://github.com/yuhonas/free-exercise-db/blob/main/exercises/Split_Squats.json | W8: Fentes bulgares sur chaise : exécution, technique, conseils et progression (français) https://www.youtube.com/watch?v=M1xhRlf8poM
A9: pont_unilateral | B9: Pont fessier sur une jambe | C9: Nouveau | G9: renforcement | H9: fessiers, jambes | I9: renforcer, tonifier | J9: 3 | K9: non | L9: aucun | M9: 10 répétitions | N9: 1. Jambe libre pliée (8 rép.) 2. Jambe libre tendue (10 rép.) 3. Pause de 2 s en haut (10 rép.) | O9: Grand fessier | P9: Ischio-jambiers, Moyen fessier, Bas du dos (lombaires) | Q9: 3 (code 02056, Renforcement au poids du corps, général) | R9: Allonge-toi sur le dos, un pied à plat, l'autre jambe en l'air. Pousse dans le talon au sol et monte le bassin bien droit. Redescends lentement. Change de jambe à mi-série. | S9: Le bassin reste horizontal : s'il penche, reviens au pont sur deux jambes. | T9: Expire en montant, inspire en redescendant. | U9: Bassin qui penche du côté de la jambe levée. Cambrer le dos en haut. | V9: free-exercise-db (domaine public), fiche Single Leg Glute Bridge : https://github.com/yuhonas/free-exercise-db/blob/main/exercises/Single_Leg_Glute_Bridge.json | W9: Pont fessier à une jambe : single leg glute bridge (français) https://www.youtube.com/watch?v=43qFZebHGj8
A10: hip_thrust | B10: Hip thrust, épaules sur le canapé | C10: Nouveau | G10: renforcement | H10: fessiers | I10: renforcer, tonifier | J10: 3 | K10: non | L10: aucun | M10: 12 répétitions | N10: 1. Poids du corps (10 rép.) 2. Poids du corps, pause de 2 s (12 rép.) 3. Haltère posé sur le bassin (12 rép.) 4. Une jambe (8 rép.) | O10: Grand fessier | P10: Ischio-jambiers, Quadriceps | Q10: 3 (code 02056, Renforcement au poids du corps, général) | R10: Assieds-toi au sol, le haut du dos appuyé contre le bord d'un canapé ou d'un lit. Pieds à plat, pousse dans les talons pour monter le bassin jusqu'à l'horizontale. Menton rentré, serre les fessiers en haut, puis redescends. | S10: Le support doit être stable et bas (hauteur de genou environ). | T10: Expire en montant, inspire en redescendant. | U10: Cambrer le bas du dos en haut. Regarder le plafond : la nuque se casse. | V10: free-exercise-db (domaine public), fiche Barbell Hip Thrust : https://github.com/yuhonas/free-exercise-db/blob/main/exercises/Barbell_Hip_Thrust.json | W10: Tuto : muscler les fessiers avec le hip thrust (Decathlon) (français) https://www.youtube.com/watch?v=34xR5kn02xY
A11: ruade | B11: Ruade (donkey kick) | C11: Nouveau | G11: renforcement | H11: fessiers | I11: tonifier, renforcer | J11: 2 | K11: non | L11: aucun | M11: 12 répétitions | N11: 1. Petite amplitude (10 rép.) 2. Amplitude complète (12 rép.) 3. Élastique autour des cuisses (12 rép.) 4. Pause de 2 s en haut (15 rép.) | O11: Grand fessier | P11: Ischio-jambiers, Abdominaux profonds | Q11: 3 (code 02056, Renforcement au poids du corps, général) | R11: À quatre pattes, mains sous les épaules, genoux sous les hanches. Genou plié à angle droit, pousse la plante du pied vers le plafond. Reviens sans poser le genou. Change de côté à mi-série. | S11: Monte seulement tant que le dos reste plat. | T11: Expire en poussant, inspire en revenant. | U11: Creuser le dos pour monter plus haut. Ouvrir la hanche sur le côté. | V11: free-exercise-db (domaine public), fiche Glute Kickback : https://github.com/yuhonas/free-exercise-db/blob/main/exercises/Glute_Kickback.json | W11: How To: Donkey Kicks for Glute Strength (anglais) https://www.youtube.com/watch?v=vElEKAdulIE
A12: bouche_incendie | B12: Bouche d'incendie (fire hydrant) | C12: Nouveau | G12: renforcement | H12: fessiers | I12: tonifier, renforcer | J12: 2 | K12: non | L12: aucun | M12: 12 répétitions | N12: 1. Petite amplitude (10 rép.) 2. Amplitude complète (12 rép.) 3. Élastique autour des cuisses (12 rép.) | O12: Moyen fessier | P12: Grand fessier, Abdominaux profonds | Q12: 3 (code 02056, Renforcement au poids du corps, général) | R12: À quatre pattes, dos plat. Garde le genou plié et ouvre la cuisse sur le côté, comme une porte. Redescends lentement. Change de côté à mi-série. | S12: Le buste ne bascule pas : seule la jambe bouge. | T12: Expire en ouvrant, inspire en refermant. | U12: Pencher tout le corps du côté opposé. Aller trop vite. | V12: free-exercise-db (domaine public), fiche Thigh Abductor : https://github.com/yuhonas/free-exercise-db/blob/main/exercises/Thigh_Abductor.json | W12: Fire hydrants : exécution, technique, conseils et progression (français) https://www.youtube.com/watch?v=6yoip-ClM34
A13: charniere_hanche | B13: Charnière de hanche (good morning) au poids du corps | C13: Nouveau | G13: renforcement | H13: jambes, dos, fessiers | I13: renforcer, mobilite | J13: 2 | K13: non | L13: aucun | M13: 12 répétitions | N13: 1. Mains sur les hanches (10 rép.) 2. Mains derrière la tête (12 rép.) 3. Élastique sous les pieds, sur la nuque (12 rép.) | O13: Ischio-jambiers, Grand fessier | P13: Bas du dos (lombaires) | Q13: 3 (code 02056, Renforcement au poids du corps, général) | R13: Debout, pieds largeur de hanches, genoux légèrement fléchis. Pousse les fesses loin en arrière, le buste descend dos plat. Arrête quand tu sens l'arrière des cuisses tirer, puis remonte en serrant les fessiers. | S13: Le dos reste plat du début à la fin : c'est la hanche qui plie. | T13: Inspire en descendant, expire en remontant. | U13: Arrondir le dos. Plier les genoux comme pour un squat. | V13: free-exercise-db (domaine public), fiche Band Good Morning : https://github.com/yuhonas/free-exercise-db/blob/main/exercises/Band_Good_Morning.json | W13: How to Do a Good Morning Exercise (Perfect Hip Hinge Form for Beginners) (anglais) https://www.youtube.com/watch?v=9ylRcYLSz40
... A15: squat_goblet | B15: Squat goblet à l'haltère | C15: Nouveau | G15: renforcement | H15: jambes, fessiers | I15: renforcer | J15: 3 | K15: non | L15: halteres | M15: 10 répétitions | N15: 1. Haltère léger (10 rép.) 2. Haltère moyen (10 rép.) 3. Pause de 2 s en bas (10 rép.) 4. Haltère lourd (8 rép.) | O15: Quadriceps, Grand fessier | P15: Adducteurs, Abdominaux profonds, Bas du dos (lombaires) | Q15: 5 (code 02052, Squats et soulevés de terre) | R15: Tiens un haltère vertical contre la poitrine, coudes vers le bas. Descends en squat, les coudes passent entre les genoux. Remonte en poussant dans les talons, buste droit. | S15: L'haltère reste collé à la poitrine pendant tout le mouvement. | T15: Inspire en descendant, expire en remontant. | U15: Laisser l'haltère tirer le buste vers l'avant. Talons qui décollent. | V15: free-exercise-db (domaine public), fiche Goblet Squat : https://github.com/yuhonas/free-exercise-db/blob/main/exercises/Goblet_Squat.json | W15: Goblet squat : exécution, technique, conseils et progression (français) https://www.youtube.com/watch?v=QNPVhVsJS2A
A16: releve_mollets_unipodal | B16: Montée sur pointe, une jambe | C16: Nouveau | G16: renforcement | H16: jambes | I16: renforcer, tonifier | J16: 2 | K16: non | L16: mur | M16: 12 répétitions | N16: 1. Main au mur, amplitude confortable (10 rép.) 2. Descente lente en 3 s (12 rép.) 3. Talon dans le vide, sur une marche (12 rép.) | O16: Mollets | Q16: 3 (code 02056, Renforcement au poids du corps, général) | R16: Debout sur une jambe, une main au mur pour l'équilibre. Monte le plus haut possible sur la pointe du pied. Redescends lentement. Change de jambe. | S16: Le genou reste juste déverrouillé. | T16: Expire en montant, inspire en descendant. | U16: Rebondir en bas. Cheville qui part vers l'extérieur. | V16: free-exercise-db (domaine public), fiche Standing Dumbbell Calf Raise : https://github.com/yuhonas/free-exercise-db/blob/main/exercises/Standing_Dumbbell_Calf_Raise.json | W16: Mollets : mollets debout à une jambe (français) https://www.youtube.com/watch?v=jGUplusFlEY
A17: adducteurs_couche | B17: Levée de jambe intérieure (adducteurs) | C17: Nouveau | G17: renforcement | H17: jambes | I17: tonifier, renforcer | J17: 1 | K17: non | L17: aucun | M17: 15 répétitions | N17: 1. Petite amplitude (12 rép.) 2. Pause de 2 s en haut (15 rép.) 3. Élastique aux chevilles (15 rép.) | O17: Adducteurs | P17: Abdominaux profonds | Q17: 3 (code 02056, Renforcement au poids du corps, général) | R17: Allonge-toi sur le côté, la jambe du dessus pliée et posée devant toi. Monte la jambe du dessous tendue, de quelques centimètres. Redescends sans poser complètement. Change de côté. | S17: Petit mouvement, sans élan. | T17: Expire en montant, inspire en descendant. | U17: Rouler vers l'arrière. Pointe du pied tournée vers le plafond. | V17: free-exercise-db (domaine public), fiche Thigh Adductor : https://github.com/yuhonas/free-exercise-db/blob/main/exercises/Thigh_Adductor.json free-exercise-db (domaine public), fiche Band Hip Adductions : https://github.com/yuhonas/free-exercise-db/blob/main/exercises/Band_Hip_Adductions.json | W17: Exercice intérieur des cuisses (adducteurs) : levé de jambe allongé (français) https://www.youtube.com/watch?v=3EiBfcTLZDE
A18: pont_marche | B18: Pont fessier en marche | C18: Nouveau | G18: gainage | H18: fessiers, abdos | I18: renforcer | J18: 3 | K18: non | L18: aucun | M18: 10 répétitions | N18: 1. Pied soulevé de 5 cm (8 rép.) 2. Genou ramené vers la poitrine (10 rép.) 3. Pause de 2 s par pas (10 rép.) | O18: Grand fessier, Abdominaux profonds | P18: Ischio-jambiers, Obliques | Q18: 2.8 (code 02024, Callisthénie légère (crunchs, planche)) | R18: En position de pont, bassin levé. Soulève un pied, puis l'autre, comme si tu marchais sur place. Le bassin reste haut et immobile. | S18: Si le bassin tourne ou descend, reviens au pont classique. | T18: Respire à chaque pas, sans bloquer. | U18: Bassin qui s'affaisse. Hanches qui basculent d'un côté à l'autre. | V18: free-exercise-db (domaine public), fiche Butt Lift Bridge : https://github.com/yuhonas/free-exercise-db/blob/main/exercises/Butt_Lift_Bridge.json | W18: How to Do a Glute Bridge March (anglais) https://www.youtube.com/watch?v=8-invS7-Ugo
A19: squat_unipodal_chaise | B19: Squat sur une jambe vers une chaise | C19: Nouveau | G19: calisthenie | H19: jambes, fessiers | I19: renforcer | J19: 4 | K19: non | L19: chaise | M19: 6 répétitions | N19: 1. Chaise haute, une main au mur (5 rép.) 2. Chaise haute (6 rép.) 3. Chaise basse (6 rép.) 4. Descente lente en 4 s (6 rép.) | O19: Quadriceps, Grand fessier | P19: Moyen fessier, Ischio-jambiers, Abdominaux profonds | Q19: 3.8 (code 02022, Callisthénie modérée (pompes, fentes)) | R19: Debout devant une chaise, sur une jambe, l'autre tendue devant toi. Descends lentement jusqu'à t'asseoir, bras tendus devant pour l'équilibre. Relève-toi sur la même jambe. Change de jambe. | S19: Étape vers le pistol squat. Pose les deux pieds si le genou rentre vers l'intérieur. | T19: Inspire en descendant, expire en te relevant. | U19: Se laisser tomber sur la chaise. Genou qui part vers l'intérieur. | V19: free-exercise-db (domaine public), fiche Single-Leg High Box Squat : https://github.com/yuhonas/free-exercise-db/blob/main/exercises/Single-Leg_High_Box_Squat.json free-exercise-db (domaine public), fiche Kettlebell Pistol Squat : https://github.com/yuhonas/free-exercise-db/blob/main/exercises/Kettlebell_Pistol_Squat.json | W19: Pistol squat, squat à 1 jambe (alternatives et progression) (français) https://www.youtube.com/watch?v=STa-MCOn3xM
A20: pompe_mur | B20: Pompe au mur | C20: Nouveau | G20: renforcement | H20: bras, epaules | I20: renforcer, tonifier | J20: 1 | K20: non | L20: mur | M20: 12 répétitions | N20: 1. Pieds proches du mur (10 rép.) 2. Pieds plus éloignés (12 rép.) 3. Descente lente en 3 s (12 rép.) | O20: Pectoraux, Triceps | P20: Épaules (avant), Abdominaux profonds | Q20: 3 (code 02056, Renforcement au poids du corps, général) | R20: Face au mur, mains à plat à hauteur d'épaules, un peu plus écartées. Plie les coudes pour approcher la poitrine du mur, corps gainé. Repousse le mur pour revenir. | S20: Plus les pieds sont loin du mur, plus c'est difficile. | T20: Inspire en descendant, expire en poussant. | U20: Coudes ouverts à 90° du corps. Fesses en arrière. | V20: NHS, Strength exercises : https://www.nhs.uk/live-well/exercise/strength-and-flexibility-exercises/strength-exercises/ free-exercise-db (domaine public), fiche Incline Push-Up : https://github.com/yuhonas/free-exercise-db/blob/main/exercises/Incline_Push-Up.json | W20: Pompes contre le mur pour débutants (français) https://www.youtube.com/watch?v=emhF1efZ-38
A21: pompe_inclinee | B21: Pompe inclinée (mains sur une chaise) | C21: Nouveau | G21: renforcement | H21: bras, epaules | I21: renforcer, tonifier | J21: 2 | K21: non | L21: chaise | M21: 10 répétitions | N21: 1. Mains sur un plan haut (table) (8 rép.) 2. Mains sur l'assise (10 rép.) 3. Descente lente en 3 s (10 rép.) | O21: Pectoraux, Triceps | P21: Épaules (avant), Abdominaux profonds | Q21: 3.8 (code 02022, Callisthénie modérée (pompes, fentes)) | R21: Mains sur l'assise d'une chaise calée contre le mur, corps en planche. Descends la poitrine vers la chaise, coudes à 45° du corps. Pousse pour revenir, corps bien aligné. | S21: La chaise ne doit pas pouvoir glisser. | T21: Inspire en descendant, expire en poussant. | U21: Bassin qui s'affaisse. Tête qui avance vers la chaise. | V21: free-exercise-db (domaine public), fiche Incline Push-Up : https://github.com/yuhonas/free-exercise-db/blob/main/exercises/Incline_Push-Up.json | W21: Pompes inclinées (français) https://www.youtube.com/watch?v=pH9hQDirfog
A22: pompe_genoux | B22: Pompe sur les genoux | C22: Nouveau | G22: renforcement | H22: bras, epaules | I22: renforcer, tonifier | J22: 2 | K22: non | L22: aucun | M22: 10 répétitions | N22: 1. Demi-amplitude (8 rép.) 2. Amplitude complète (10 rép.) 3. Descente lente en 3 s (10 rép.) | O22: Pectoraux, Triceps | P22: Épaules (avant), Abdominaux profonds | Q22: 3.8 (code 02022, Callisthénie modérée (pompes, fentes)) | R22: À genoux, mains au sol sous les épaules, un peu plus écartées. Aligne genoux, hanches et épaules, puis descends la poitrine vers le sol. Repousse le sol pour remonter. | S22: Un coussin sous les genoux rend l'exercice plus confortable. | T22: Inspire en descendant, expire en poussant. | U22: Fesses en l'air. Coudes ouverts sur les côtés. | V22: free-exercise-db (domaine public), fiche Pushups : https://github.com/yuhonas/free-exercise-db/blob/main/exercises/Pushups.json | W22: Pompe sur les genoux : démonstration, explication et conseils (français) https://www.youtube.com/watch?v=SWUw2epT8P4
A23: pompe | B23: Pompe | C23: Nouveau | G23: calisthenie | H23: bras, epaules, abdos | I23: renforcer | J23: 3 | K23: non | L23: aucun | M23: 10 répétitions | N23: 1. 5 pompes propres (5 rép.) 2. 8 pompes (8 rép.) 3. 10 pompes (10 rép.) 4. Descente lente en 3 s (10 rép.) | O23: Pectoraux, Triceps | P23: Épaules (avant), Abdominaux (grand droit), Abdominaux profonds | Q23: 3.8 (code 02022, Callisthénie modérée (pompes, fentes)) | R23: Mains au sol un peu plus larges que les épaules, corps droit de la tête aux talons. Descends la poitrine jusqu'à quelques centimètres du sol, coudes à 45°. Pousse le sol pour revenir, sans casser l'alignement. | S23: Si le bassin s'affaisse, passe à la pompe sur les genoux. | T23: Inspire en descendant, expire en poussant. | U23: Bassin qui s'affaisse. Tête qui plonge vers le sol. Coudes à 90° du corps. | V23: free-exercise-db (domaine public), fiche Pushups : https://github.com/yuhonas/free-exercise-db/blob/main/exercises/Pushups.json | W23: Comment bien faire les pompes (évitez les erreurs courantes et progressez) (français) https://www.youtube.com/watch?v=V9TUK5IdRrY
A24: pompe_serree | B24: Pompe mains serrées (triceps) | C24: Nouveau | G24: calisthenie | H24: bras | I24: renforcer | J24: 4 | K24: non | L24: aucun | M24: 8 répétitions | N24: 1. Sur les genoux (8 rép.) 2. Sur les pieds (6 rép.) 3. Sur les pieds (8 rép.) | O24: Triceps | P24: Pectoraux, Épaules (avant) | Q24: 3.8 (code 02022, Callisthénie modérée (pompes, fentes)) | R24: En position de pompe, mains sous les épaules, rapprochées. Descends en gardant les coudes collés au corps. Pousse pour remonter. | S24: Plus exigeant pour les poignets : écarte un peu les mains si besoin. | T24: Inspire en descendant, expire en poussant. | U24: Coudes qui s'ouvrent. Bassin qui s'affaisse. | V24: free-exercise-db (domaine public), fiche Push-Ups - Close Triceps Position : https://github.com/yuhonas/free-exercise-db/blob/main/exercises/Push-Ups_-_Close_Triceps_Position.json | W24: Les pompes prise serrée pour les triceps (pour qui, comment, variantes) (français) https://www.youtube.com/watch?v=FvnPL4cYUQk
A25: pompe_pike | B25: Pompe en V (pike push-up) | C25: Nouveau | G25: calisthenie | H25: epaules, bras | I25: renforcer | J25: 4 | K25: non | L25: aucun | M25: 8 répétitions | N25: 1. Petite amplitude (6 rép.) 2. Front vers le sol (8 rép.) 3. Pieds surélevés sur une chaise (6 rép.) | O25: Épaules (avant), Triceps | P25: Trapèzes, Pectoraux | Q25: 3.8 (code 02022, Callisthénie modérée (pompes, fentes)) | R25: Mains au sol, fesses hautes : ton corps forme un V à l'envers. Plie les coudes pour descendre le sommet du crâne vers le sol, entre les mains. Repousse pour revenir. | S25: Descends lentement : le poids est sur les épaules et la tête approche du sol. | T25: Inspire en descendant, expire en poussant. | U25: Coudes qui partent sur les côtés. Fesses qui descendent : ça devient une pompe classique. | V25: free-exercise-db (domaine public), fiche Handstand Push-Ups : https://github.com/yuhonas/free-exercise-db/blob/main/exercises/Handstand_Push-Ups.json | W25: Pike push up (niveau 1) (français) https://www.youtube.com/watch?v=NrkGYnsgbOA
A26: dips_chaise | B26: Dips sur chaise | C26: Nouveau | G26: calisthenie | H26: bras | I26: renforcer, tonifier | J26: 3 | K26: non | L26: chaise | M26: 10 répétitions | N26: 1. Genoux pliés, petite amplitude (8 rép.) 2. Genoux pliés (10 rép.) 3. Jambes tendues (10 rép.) | O26: Triceps | P26: Pectoraux, Épaules (avant) | Q26: 3.8 (code 02022, Callisthénie modérée (pompes, fentes)) | R26: Dos à une chaise stable, mains sur le bord de l'assise, doigts vers l'avant. Plie les coudes vers l'arrière pour descendre les fesses. Remonte en tendant les bras. | S26: Descends jusqu'à ce que les bras soient à angle droit, pas plus bas. | T26: Inspire en descendant, expire en poussant. | U26: Épaules qui remontent vers les oreilles. Coudes qui s'écartent. S'éloigner de la chaise. | V26: free-exercise-db (domaine public), fiche Bench Dips : https://github.com/yuhonas/free-exercise-db/blob/main/exercises/Bench_Dips.json | W26: Dips sur chaise : exécution, technique, conseils et progression (français) https://www.youtube.com/watch?v=hIB3YWZk834
A27: rowing_haltere | B27: Rowing à un bras à l'haltère | C27: Nouveau | G27: renforcement | H27: dos, bras | I27: renforcer, tonifier | J27: 2 | K27: non | L27: halteres | M27: 12 répétitions | N27: 1. Haltère léger (12 rép.) 2. Haltère moyen (10 rép.) 3. Pause de 2 s coude en arrière (10 rép.) | O27: Grand dorsal, Haut du dos (rhomboïdes) | P27: Biceps, Épaules (arrière) | Q27: 3.5 (code 02054, Renforcement, 8 à 15 répétitions, résistance variée) | R27: Une main et un genou sur une chaise, l'autre pied au sol, dos plat. Tire l'haltère vers la hanche, coude près du corps. Redescends lentement. Change de côté. | S27: Le dos reste plat et immobile, sans rotation. | T27: Expire en tirant, inspire en descendant. | U27: Tourner le buste pour monter l'haltère. Tirer vers l'épaule au lieu de la hanche. | V27: free-exercise-db (domaine public), fiche One-Arm Dumbbell Row : https://github.com/yuhonas/free-exercise-db/blob/main/exercises/One-Arm_Dumbbell_Row.json | W27: Musculation du dos : le rowing haltère à 1 bras (français) https://www.youtube.com/watch?v=VLzDhlGdpS0
A28: developpe_epaules | B28: Développé épaules aux haltères | C28: Nouveau | G28: renforcement | H28: epaules, bras | I28: renforcer, tonifier | J28: 3 | K28: non | L28: halteres | M28: 10 répétitions | N28: 1. Assis, haltères légers (10 rép.) 2. Debout (10 rép.) 3. Haltères moyens (10 rép.) | O28: Épaules (avant), Épaules (côté) | P28: Triceps, Trapèzes | Q28: 3.5 (code 02054, Renforcement, 8 à 15 répétitions, résistance variée) | R28: Haltères à hauteur d'épaules, paumes vers l'avant, ventre gainé. Pousse vers le haut jusqu'à tendre les bras. Redescends lentement à hauteur d'oreilles. | S28: Ne cambre pas le bas du dos pour pousser : allège la charge. | T28: Expire en poussant, inspire en descendant. | U28: Cambrer le dos. Descendre trop vite. | V28: free-exercise-db (domaine public), fiche Dumbbell Shoulder Press : https://github.com/yuhonas/free-exercise-db/blob/main/exercises/Dumbbell_Shoulder_Press.json | W28: Technique du développé épaules aux haltères (assis ou debout) (français) https://www.youtube.com/watch?v=CE9KiCPFw0E
A29: curl_marteau | B29: Curl marteau aux haltères | C29: Nouveau | G29: renforcement | H29: bras | I29: renforcer, tonifier | J29: 2 | K29: non | L29: halteres | M29: 12 répétitions | N29: 1. Haltères légers (12 rép.) 2. Haltères moyens (10 rép.) 3. Descente lente en 3 s (10 rép.) | O29: Biceps, Avant-bras | Q29: 3.5 (code 02054, Renforcement, 8 à 15 répétitions, résistance variée) | R29: Debout, un haltère dans chaque main, paumes face à face. Plie les coudes pour monter les haltères vers les épaules. Redescends lentement, coudes collés au corps. | S29: Pas d'élan avec le dos. | T29: Expire en montant, inspire en descendant. | U29: Balancer le buste. Coudes qui avancent. | V29: free-exercise-db (domaine public), fiche Hammer Curls : https://github.com/yuhonas/free-exercise-db/blob/main/exercises/Hammer_Curls.json | W29: Comment faire un curl marteau : technique correcte pour les biceps (français) https://www.youtube.com/watch?v=CsZSbMuqDYw
A30: extension_triceps_haltere | B30: Extension des triceps au-dessus de la tête | C30: Nouveau | G30: renforcement | H30: bras | I30: renforcer, tonifier | J30: 2 | K30: non | L30: halteres | M30: 12 répétitions | N30: 1. Assis, haltère léger (12 rép.) 2. Debout (12 rép.) 3. Haltère moyen (10 rép.) | O30: Triceps | Q30: 3.5 (code 02054, Renforcement, 8 à 15 répétitions, résistance variée) | R30: Tiens un haltère à deux mains au-dessus de la tête. Plie les coudes pour descendre l'haltère derrière la nuque. Tends les bras pour remonter, coudes pointés vers l'avant. | S30: Garde les côtes basses : pas de cambrure. | T30: Inspire en descendant, expire en tendant. | U30: Coudes qui s'écartent. Cambrer le dos. | V30: free-exercise-db (domaine public), fiche Standing Dumbbell Triceps Extension : https://github.com/yuhonas/free-exercise-db/blob/main/exercises/Standing_Dumbbell_Triceps_Extension.json | W30: Extension triceps avec haltère : démonstration, muscles, variantes, conseils et progression (français) https://www.youtube.com/watch?v=Reitru3_Srk
A31: oiseau_haltere | B31: Oiseau aux haltères (arrière d'épaule) | C31: Nouveau | G31: renforcement | H31: epaules, dos | I31: renforcer, tonifier | J31: 2 | K31: non | L31: halteres | M31: 12 répétitions | N31: 1. Haltères très légers (12 rép.) 2. Pause de 2 s bras ouverts (12 rép.) 3. Haltères légers (12 rép.) | O31: Épaules (arrière), Haut du dos (rhomboïdes) | P31: Trapèzes | Q31: 3.5 (code 02054, Renforcement, 8 à 15 répétitions, résistance variée) | R31: Penché en avant, dos plat, genoux fléchis, haltères sous les épaules. Ouvre les bras sur les côtés, coudes légèrement fléchis. Serre les omoplates en haut, puis redescends lentement. | S31: Des charges très légères suffisent. | T31: Expire en ouvrant, inspire en redescendant. | U31: Se redresser pour monter les bras. Hausser les épaules. | V31: free-exercise-db (domaine public), fiche Bent Over Low-Pulley Side Lateral : https://github.com/yuhonas/free-exercise-db/blob/main/exercises/Bent_Over_Low-Pulley_Side_Lateral.json | W31: Oiseau buste penché avec haltères (français) https://www.youtube.com/watch?v=mzbY2Vd0Mts
A32: developpe_sol | B32: Développé au sol aux haltères | C32: Nouveau | G32: renforcement | H32: bras, epaules | I32: renforcer | J32: 2 | K32: non | L32: halteres | M32: 12 répétitions | N32: 1. Haltères légers (12 rép.) 2. Haltères moyens (10 rép.) 3. Pause de 1 s coudes au sol (10 rép.) | O32: Pectoraux, Triceps | P32: Épaules (avant) | Q32: 3.5 (code 02054, Renforcement, 8 à 15 répétitions, résistance variée) | R32: Allongé sur le dos, genoux pliés, un haltère dans chaque main. Pousse les haltères vers le plafond jusqu'à tendre les bras. Redescends jusqu'à poser doucement les coudes au sol. | S32: Coudes à environ 45° du corps. | T32: Expire en poussant, inspire en descendant. | U32: Laisser tomber les coudes au sol. Coudes à angle droit du corps. | V32: free-exercise-db (domaine public), fiche Dumbbell Floor Press : https://github.com/yuhonas/free-exercise-db/blob/main/exercises/Dumbbell_Floor_Press.json | W32: Développé couché au sol : un développé couché pas comme les autres (français) https://www.youtube.com/watch?v=WVfLGkuhHHU
A33: tirage_vertical_elastique | B33: Tirage vertical à l'élastique | C33: Nouveau | G33: renforcement | H33: dos, bras | I33: renforcer, tonifier | J33: 2 | K33: non | L33: elastique | M33: 12 répétitions | N33: 1. Élastique léger (12 rép.) 2. Élastique moyen (12 rép.) 3. Pause de 2 s en bas (10 rép.) | O33: Grand dorsal | P33: Biceps, Haut du dos (rhomboïdes) | Q33: 3.5 (code 02054, Renforcement, 8 à 15 répétitions, résistance variée) | R33: Élastique fixé en haut d'une porte fermée, à genoux face à la porte. Bras tendus vers le haut, tire les coudes vers les côtes. Remonte lentement en gardant les épaules basses. | S33: Vérifie que l'élastique est bien coincé dans une porte fermée à clé ou ouvrant vers l'extérieur. | T33: Expire en tirant, inspire en remontant. | U33: Se pencher en arrière. Hausser les épaules. | V33: free-exercise-db (domaine public), fiche Band Assisted Pull-Up : https://github.com/yuhonas/free-exercise-db/blob/main/exercises/Band_Assisted_Pull-Up.json | W33: Tirage vertical à l'élastique (français) https://www.youtube.com/watch?v=8rSNwrdPgN4
A34: developpe_elastique | B34: Développé épaules à l'élastique | C34: Nouveau | G34: renforcement | H34: epaules | I34: renforcer, tonifier | J34: 2 | K34: non | L34: elastique | M34: 12 répétitions | N34: 1. Élastique léger (12 rép.) 2. Élastique moyen (12 rép.) 3. Un bras à la fois (10 rép.) | O34: Épaules (avant), Épaules (côté) | P34: Triceps | Q34: 3.5 (code 02054, Renforcement, 8 à 15 répétitions, résistance variée) | R34: Debout sur l'élastique, mains à hauteur d'épaules. Pousse vers le haut jusqu'à tendre les bras. Redescends lentement. | S34: Ventre gainé, sans cambrer. | T34: Expire en poussant, inspire en descendant. | U34: Cambrer le dos. Pousser vers l'avant au lieu du haut. | V34: free-exercise-db (domaine public), fiche Shoulder Press - With Bands : https://github.com/yuhonas/free-exercise-db/blob/main/exercises/Shoulder_Press_-_With_Bands.json | W34: Développé militaire élastique : exercice debout pour les épaules (français) https://www.youtube.com/watch?v=Y28EDAb2ASY
A35: superman | B35: Superman | C35: Nouveau | G35: renforcement | H35: dos, fessiers | I35: renforcer | J35: 2 | K35: non | L35: aucun | M35: 10 répétitions | N35: 1. Bras seuls, puis jambes seules (8 rép.) 2. Bras et jambes ensemble (10 rép.) 3. Maintien de 3 s en haut (10 rép.) | O35: Bas du dos (lombaires), Grand fessier | P35: Haut du dos (rhomboïdes), Ischio-jambiers | Q35: 3.5 (code 02030, Callisthénie légère à modérée (exercices du dos, se relever du sol)) | R35: Allongé sur le ventre, bras tendus devant toi, front au sol. Décolle en même temps bras et jambes de quelques centimètres. Redescends lentement. | S35: Petite hauteur suffit : le regard reste vers le sol. | T35: Expire en montant, inspire en descendant. | U35: Lever la tête vers l'avant. Monter trop haut en forçant sur le bas du dos. | V35: free-exercise-db (domaine public), fiche Superman : https://github.com/yuhonas/free-exercise-db/blob/main/exercises/Superman.json | W35: Comment se muscler les lombaires et le bas du dos : superman (français) https://www.youtube.com/watch?v=O-DOcsnwAQY
A36: ytw | B36: Y, T, W au sol | C36: Nouveau | G36: renforcement | H36: dos, epaules | I36: renforcer, mobilite | J36: 2 | K36: non | L36: aucun | M36: 9 répétitions | N36: 1. 2 de chaque lettre (6 rép.) 2. 3 de chaque lettre (9 rép.) 3. 3 de chaque, pause de 2 s (9 rép.) | O36: Haut du dos (rhomboïdes), Trapèzes, Épaules (arrière) | P36: Coiffe des rotateurs, Bas du dos (lombaires) | Q36: 3.5 (code 02030, Callisthénie légère à modérée (exercices du dos, se relever du sol)) | R36: Allongé sur le ventre, front sur une serviette roulée. Décolle les bras en Y, puis en T, puis en W (coudes pliés, ramenés vers les côtes). Pouces vers le plafond, serre les omoplates à chaque lettre. | S36: Mouvement lent, épaules loin des oreilles. | T36: Expire en décollant les bras, inspire en les reposant. | U36: Décoller la poitrine en cambrant. Aller trop vite. | V36: free-exercise-db (domaine public), fiche Reverse Flyes With External Rotation : https://github.com/yuhonas/free-exercise-db/blob/main/exercises/Reverse_Flyes_With_External_Rotation.json | W36: Posture : l'exercice des lettres I, Y, T, W, A (français) https://www.youtube.com/watch?v=G0nPXt_TgRg
A37: rowing_inverse_table | B37: Rowing inversé sous une table | C37: Nouveau | G37: calisthenie | H37: dos, bras | I37: renforcer | J37: 4 | K37: non | L37: aucun | M37: 8 répétitions | N37: 1. Genoux pliés (6 rép.) 2. Genoux pliés (8 rép.) 3. Jambes tendues (8 rép.) | O37: Grand dorsal, Haut du dos (rhomboïdes) | P37: Biceps, Épaules (arrière), Abdominaux profonds | Q37: 3.8 (code 02022, Callisthénie modérée (pompes, fentes)) | R37: Allongé sous une table très solide, mains sur le bord, bras tendus. Corps gainé, tire la poitrine vers le bord de la table. Redescends lentement. | S37: Seulement avec une table lourde et stable qui ne peut pas basculer. Teste-la avant. | T37: Expire en tirant, inspire en redescendant. | U37: Bassin qui s'affaisse. Tirer avec le cou. | V37: free-exercise-db (domaine public), fiche Inverted Row : https://github.com/yuhonas/free-exercise-db/blob/main/exercises/Inverted_Row.json | W37: Rowing inversé sous une table : exercice pour renforcer le dos (français) https://www.youtube.com/watch?v=lcsEJQAbdiw
A38: crunch | B38: Crunch | C38: Nouveau | G38: renforcement | H38: abdos | I38: tonifier, renforcer | J38: 2 | K38: non | L38: aucun | M38: 15 répétitions | N38: 1. Mains sur les cuisses (12 rép.) 2. Mains croisées sur la poitrine (15 rép.) 3. Pause de 2 s en haut (15 rép.) | O38: Abdominaux (grand droit) | P38: Obliques | Q38: 2.8 (code 02024, Callisthénie légère (crunchs, planche)) | R38: Allongé sur le dos, genoux pliés, pieds à plat. Enroule le haut du dos pour décoller les omoplates. Redescends lentement sans reposer complètement la tête. | S38: Ne tire pas sur la nuque avec les mains. | T38: Expire en montant, inspire en redescendant. | U38: Tirer sur la tête. Monter trop haut avec élan. | V38: free-exercise-db (domaine public), fiche Crunches : https://github.com/yuhonas/free-exercise-db/blob/main/exercises/Crunches.json | W38: Comment bien faire les crunchs pour les abdos (français) https://www.youtube.com/watch?v=LEb7Juw9tMo
A39: crunch_inverse | B39: Crunch inversé | C39: Nouveau | G39: renforcement | H39: abdos | I39: tonifier, renforcer | J39: 2 | K39: non | L39: aucun | M39: 12 répétitions | N39: 1. Petite amplitude (10 rép.) 2. Bassin décollé (12 rép.) 3. Descente lente en 3 s (12 rép.) | O39: Abdominaux (grand droit) | P39: Obliques, Fléchisseurs de hanche | Q39: 2.8 (code 02024, Callisthénie légère (crunchs, planche)) | R39: Allongé sur le dos, genoux pliés au-dessus des hanches, bras le long du corps. Ramène les genoux vers la poitrine en décollant légèrement le bassin. Redescends lentement. | S39: On enroule le bassin, on ne balance pas les jambes. | T39: Expire en enroulant, inspire en revenant. | U39: Prendre de l'élan. Appuyer fort sur les mains. | V39: free-exercise-db (domaine public), fiche Reverse Crunch : https://github.com/yuhonas/free-exercise-db/blob/main/exercises/Reverse_Crunch.json | W39: Musculation des abdominaux : crunch inversé (français) https://www.youtube.com/watch?v=0bq05pA3bkA
A40: crunch_velo | B40: Crunch vélo | C40: Nouveau | G40: renforcement | H40: abdos | I40: tonifier, renforcer | J40: 3 | K40: non | L40: aucun | M40: 16 répétitions | N40: 1. Pieds proches du sol en alternance lente (12 rép.) 2. 16 alternances (16 rép.) 3. 20 alternances (20 rép.) | O40: Obliques, Abdominaux (grand droit) | P40: Fléchisseurs de hanche | Q40: 2.8 (code 02024, Callisthénie légère (crunchs, planche)) | R40: Allongé sur le dos, mains aux tempes, omoplates décollées. Amène un coude vers le genou opposé pendant que l'autre jambe s'allonge. Alterne lentement, comme un pédalage. | S40: Le bas du dos reste au sol. | T40: Expire à chaque rotation. | U40: Tirer sur la nuque. Aller vite et perdre le contrôle. | V40: free-exercise-db (domaine public), fiche Cross-Body Crunch : https://github.com/yuhonas/free-exercise-db/blob/main/exercises/Cross-Body_Crunch.json free-exercise-db (domaine public), fiche Elbow to Knee : https://github.com/yuhonas/free-exercise-db/blob/main/exercises/Elbow_to_Knee.json | W40: Crunch cycliste : un exercice pour la taille (français) https://www.youtube.com/watch?v=rsX2MJPzXrE
A41: releve_jambes | B41: Relevé de jambes | C41: Nouveau | G41: renforcement | H41: abdos | I41: renforcer | J41: 3 | K41: non | L41: aucun | M41: 10 répétitions | N41: 1. Genoux pliés (10 rép.) 2. Jambes tendues, petite amplitude (8 rép.) 3. Jambes tendues (10 rép.) | O41: Abdominaux (grand droit), Fléchisseurs de hanche | P41: Abdominaux profonds | Q41: 2.8 (code 02024, Callisthénie légère (crunchs, planche)) | R41: Allongé sur le dos, mains sous les fesses. Monte les jambes jusqu'à la verticale. Redescends lentement sans que le bas du dos décolle. | S41: Arrête la descente avant que le dos ne se creuse. | T41: Expire en montant, inspire en descendant. | U41: Dos qui se creuse en bas. Jambes qui tombent. | V41: free-exercise-db (domaine public), fiche Flat Bench Lying Leg Raise : https://github.com/yuhonas/free-exercise-db/blob/main/exercises/Flat_Bench_Lying_Leg_Raise.json | W41: Exercice abdos : relevé de jambes allongé (français) https://www.youtube.com/watch?v=RNgWIsjj5U8
A42: ciseaux | B42: Battements de jambes (ciseaux) | C42: Nouveau | G42: gainage | H42: abdos | I42: tonifier, renforcer | J42: 3 | K42: non | L42: aucun | M42: 30 s | N42: 1. Jambes hautes (20 s) 2. Jambes hautes (30 s) 3. Jambes plus basses (30 s) | O42: Abdominaux (grand droit), Abdominaux profonds | P42: Fléchisseurs de hanche | Q42: 2.8 (code 02024, Callisthénie légère (crunchs, planche)) | R42: Allongé sur le dos, mains sous les fesses, jambes tendues levées. Fais de petits battements de haut en bas, en alternant. Le bas du dos reste collé au sol. | S42: Plus les jambes sont hautes, plus c'est facile. | T42: Respire régulièrement, sans bloquer. | U42: Dos qui se creuse. Grands battements trop rapides. | V42: free-exercise-db (domaine public), fiche Flutter Kicks : https://github.com/yuhonas/free-exercise-db/blob/main/exercises/Flutter_Kicks.json free-exercise-db (domaine public), fiche Scissor Kick : https://github.com/yuhonas/free-exercise-db/blob/main/exercises/Scissor_Kick.json | W42: L'exercice des ciseaux pour renforcer ses abdominaux (français) https://www.youtube.com/watch?v=a8Y_-YCnaUg
... A76: plus_grand_etirement | B76: Le plus grand étirement du monde | C76: Nouveau | G76: etirement | H76: corps_entier, jambes, dos | I76: mobilite | J76: 2 | K76: non | L76: aucun | M76: 60 s | N76: 1. Main au sol, sans rotation (45 s) 2. Avec rotation du buste (60 s) | O76: Fléchisseurs de hanche, Ischio-jambiers | P76: Obliques, Adducteurs, Haut du dos (rhomboïdes) | Q76: 2.3 (code 02101, Étirements doux) | R76: Fente avant profonde, mains au sol à l'intérieur du pied avant. Ouvre le bras côté jambe avant vers le plafond en tournant le buste. Reviens, puis change de côté à mi-temps. | S76: Pose le genou arrière au sol si besoin. | T76: Inspire en ouvrant, expire en revenant. | U76: Genou avant qui rentre vers l'intérieur. Hanche arrière qui s'affaisse. | V76: free-exercise-db (domaine public), fiche Worlds Greatest Stretch : https://github.com/yuhonas/free-exercise-db/blob/main/exercises/Worlds_Greatest_Stretch.json | W76: World's Greatest Stretch (le meilleur étirement du monde) (français) https://www.youtube.com/watch?v=_vfHhERqpbI
A77: montagne | B77: Posture de la montagne | C77: Nouveau | G77: yoga | H77: corps_entier | I77: detente, mobilite | J77: 1 | K77: non | L77: aucun | M77: 30 s | N77: 1. 30 s (30 s) 2. 45 s, yeux fermés (45 s) | O77: Abdominaux profonds | P77: Quadriceps, Grand fessier, Mollets | Q77: 2.3 (code 02150, Yoga hatha) | R77: Debout, pieds parallèles, poids réparti sur tout le pied. Grandis-toi par le sommet du crâne, épaules relâchées, bras le long du corps. Reste immobile et observe ta respiration. | T77: Respire lentement par le nez. | U77: Verrouiller les genoux. Pousser le ventre en avant. | V77: Yogamatters, bibliothèque de postures : Mountain Pose (Tadasana) : https://www.yogamatters.com/blogs/pose-library/mountain-pose-tadasana | W77: La posture de la montagne, Tadasana (français) https://www.youtube.com/watch?v=ve_cJNhiQVA
A78: salutation_soleil | B78: Salutation au soleil (version douce) | C78: Nouveau | G78: yoga | H78: corps_entier | I78: mobilite, cardio | J78: 2 | K78: non | L78: aucun | M78: 90 s | N78: 1. 2 cycles lents, genoux au sol (90 s) 2. 3 cycles (120 s) 3. 4 cycles, rythme fluide (150 s) | O78: Ischio-jambiers, Épaules (avant), Bas du dos (lombaires) | P78: Pectoraux, Triceps, Fléchisseurs de hanche | Q78: 3.5 (code 02180, Salutation au soleil) | R78: Enchaîne les postures au rythme de ta respiration : une posture, un souffle. Plie les genoux autant que nécessaire en flexion avant. Pose les genoux au sol pour la descente vers le cobra si les bras fatiguent. | S78: Va à ton rythme : la fluidité compte plus que l'amplitude. | T78: Inspire quand le corps s'ouvre, expire quand il se plie. | U78: Bloquer sa respiration. Laisser le bas du dos s'effondrer en cobra. | V78: The Yoga Institute, Surya Namaskar step by step : https://theyogainstitute.org/surya-namaskar-the-sun-salutation/ | W78: Salutation au soleil pour débutants : 3 progressions (français) https://www.youtube.com/watch?v=sFprTU_r38o
A79: chien_tete_bas | B79: Chien tête en bas | C79: Nouveau | G79: yoga | H79: corps_entier, jambes, epaules | I79: mobilite, renforcer | J79: 2 | K79: non | L79: aucun | M79: 30 s | N79: 1. Genoux bien fléchis (20 s) 2. 30 s (30 s) 3. 45 s, talons vers le sol (45 s) | O79: Ischio-jambiers, Mollets, Épaules (avant) | P79: Grand dorsal, Triceps | Q79: 2.3 (code 02150, Yoga hatha) | R79: À quatre pattes, orteils retournés. Pousse le sol avec les mains et monte les fesses vers le plafond. Dos long en priorité, genoux fléchis si besoin, talons vers le sol sans forcer. | S79: Un dos long compte plus que des jambes tendues. | T79: Respire lentement par le nez. | U79: Dos arrondi pour tendre les jambes. Épaules collées aux oreilles. | V79: Yoga Journal, Downward-Facing Dog : https://www.yogajournal.com/poses/downward-facing-dog/ | W79: Posture du chien tête en bas (Adho Mukha Svanasana) pour débuter (français) https://www.youtube.com/watch?v=Ei4a7kDbdlg
A80: cobra | B80: Cobra | C80: Nouveau | G80: yoga | H80: dos, abdos | I80: mobilite | J80: 1 | K80: non | L80: aucun | M80: 20 s | N80: 1. Petite hauteur (15 s) 2. 20 s (20 s) 3. 30 s (30 s) | O80: Bas du dos (lombaires), Abdominaux (grand droit) | P80: Pectoraux, Fléchisseurs de hanche | Q80: 2.3 (code 02150, Yoga hatha) | R80: À plat ventre, mains sous les épaules, coudes près du corps. Pousse doucement dans les mains pour décoller la poitrine. Épaules basses, regard vers l'avant, bassin au sol. | S80: Monte seulement jusqu'où le bas du dos reste confortable. | T80: Inspire en montant, puis respire calmement. | U80: Tendre les bras à fond. Hausser les épaules. | V80: Yoga Journal, Cobra Pose : https://www.yogajournal.com/poses/types/cobra-pose-2/ | W80: Apprendre la posture du cobra, Bhujangasana (français) https://www.youtube.com/watch?v=RGYgiC9319o
A81: sphinx | B81: Sphinx | C81: Nouveau | G81: yoga | H81: dos | I81: mobilite, detente | J81: 1 | K81: non | L81: aucun | M81: 45 s | N81: 1. 30 s (30 s) 2. 45 s (45 s) 3. 1 min (60 s) | O81: Bas du dos (lombaires) | P81: Abdominaux (grand droit), Pectoraux | Q81: 2.3 (code 02150, Yoga hatha) | R81: À plat ventre, avant-bras au sol, coudes sous les épaules. Laisse la poitrine s'ouvrir, nuque longue. Relâche les fessiers et les jambes. | S81: Version plus douce du cobra. | T81: Respire lentement dans le ventre. | U81: S'affaisser entre les épaules. Serrer fort les fessiers. | V81: Yoga Journal, Sphinx Pose : https://www.yogajournal.com/poses/sphinx-pose/ | W81: La posture du sphinx guidée, débutants ou seniors (français) https://www.youtube.com/watch?v=GjRvu1tYP7E
A82: guerrier_1 | B82: Guerrier I | C82: Nouveau | G82: yoga | H82: jambes, fessiers | I82: renforcer, mobilite | J82: 2 | K82: non | L82: aucun | M82: 40 s | N82: 1. 20 s par côté (40 s) 2. 30 s par côté (60 s) | O82: Quadriceps, Grand fessier | P82: Fléchisseurs de hanche, Épaules (avant) | Q82: 2.3 (code 02150, Yoga hatha) | R82: Grand pas en arrière, pied arrière tourné vers l'extérieur, talon au sol. Plie le genou avant au-dessus de la cheville, bassin face à l'avant. Lève les bras au-dessus de la tête. Change de côté à mi-temps. | S82: Raccourcis le pas si le talon arrière décolle. | T82: Respire profondément par le nez. | U82: Genou avant qui dépasse la cheville. Cambrer le dos. | V82: Yoga Journal, Warrior I Pose : https://www.yogajournal.com/pose/poses/warrior-i-pose/ | W82: Posture du guerrier 1 (Virabhadrasana) pour les débutants (français) https://www.youtube.com/watch?v=FSv689Hk49o
A83: guerrier_2 | B83: Guerrier II | C83: Nouveau | G83: yoga | H83: jambes, fessiers | I83: renforcer, mobilite | J83: 2 | K83: non | L83: aucun | M83: 40 s | N83: 1. 20 s par côté (40 s) 2. 30 s par côté (60 s) | O83: Quadriceps, Adducteurs | P83: Grand fessier, Épaules (côté) | Q83: 2.3 (code 02150, Yoga hatha) | R83: Jambes très écartées, pied avant tourné vers l'avant, pied arrière parallèle au tapis. Plie le genou avant au-dessus de la cheville. Bras ouverts à l'horizontale, regard au-dessus de la main avant. Change de côté à mi-temps. | S83: Le genou avant pointe vers le petit orteil. | T83: Respire profondément et régulièrement. | U83: Buste penché vers l'avant. Genou qui rentre vers l'intérieur. | V83: Yoga Journal, Warrior II Pose : https://www.yogajournal.com/poses/warrior-ii-pose/ | W83: Tuto yoga : le guerrier 2 à la loupe (français) https://www.youtube.com/watch?v=rtfWanShIsc
A84: triangle | B84: Triangle | C84: Nouveau | G84: yoga | H84: jambes, abdos | I84: mobilite | J84: 2 | K84: non | L84: aucun | M84: 40 s | N84: 1. Main sur le tibia, 20 s par côté (40 s) 2. 30 s par côté (60 s) | O84: Ischio-jambiers, Obliques, Adducteurs | P84: Quadriceps | Q84: 2.3 (code 02150, Yoga hatha) | R84: Jambes écartées, pied avant tourné vers l'avant, jambes tendues. Allonge le buste au-dessus de la jambe avant, puis pose la main sur le tibia. Ouvre l'autre bras vers le plafond. Change de côté à mi-temps. | S84: Garde les deux côtés du buste longs plutôt que de descendre la main plus bas. | T84: Respire dans les côtes ouvertes. | U84: Arrondir le côté du buste. Verrouiller le genou avant. | V84: Yoga Journal, Extended Triangle Pose : https://www.yogajournal.com/poses/extended-triangle-pose/ | W84: Yoga : posture du triangle, Utthita Trikonasana (français) https://www.youtube.com/watch?v=zc1zqcH52yY
A85: arbre | B85: Arbre | C85: Nouveau | G85: yoga | H85: jambes, fessiers | I85: renforcer, detente | J85: 1 | K85: non | L85: aucun | M85: 40 s | N85: 1. Pied contre la cheville, 20 s par côté (40 s) 2. Pied contre le mollet ou la cuisse (40 s) 3. 30 s par côté, bras levés (60 s) | O85: Moyen fessier, Mollets | P85: Abdominaux profonds, Adducteurs | Q85: 2.3 (code 02150, Yoga hatha) | R85: Debout sur une jambe, pose la plante du pied libre contre la cheville, le mollet ou la cuisse. Mains jointes devant la poitrine, regard fixé sur un point. Change de jambe à mi-temps. | S85: Jamais le pied contre le genou. Une main au mur au début, si besoin. | T85: Respiration calme et lente. | U85: Pied appuyé sur le genou. Hanche qui sort sur le côté. | V85: Yoga Journal, Tree Pose : https://www.yogajournal.com/poses/types/tree-pose-2/ | W85: Yoga : posture de l'arbre, Vrikshasana (français) https://www.youtube.com/watch?v=t8KXifZclxM
A86: chaise_yoga | B86: Posture de la chaise | C86: Nouveau | G86: yoga | H86: jambes, fessiers | I86: renforcer | J86: 2 | K86: non | L86: aucun | M86: 30 s | N86: 1. 20 s (20 s) 2. 30 s (30 s) 3. 45 s (45 s) | O86: Quadriceps, Grand fessier | P86: Épaules (avant), Bas du dos (lombaires) | Q86: 2.3 (code 02150, Yoga hatha) | R86: Pieds joints, plie les genoux comme pour t'asseoir. Lève les bras dans le prolongement du buste. Poids sur les talons, genoux derrière les orteils. | S86: Bras devant toi si les épaules sont raides. | T86: Respire profondément pendant le maintien. | U86: Cambrer le bas du dos. Genoux qui dépassent largement les orteils. | V86: Yoga Journal, Chair Pose : https://www.yogajournal.com/poses/chair-pose-2/ | W86: Comment faire la posture de la chaise, Utkatasana (français) https://www.youtube.com/watch?v=h3anl2PgCHA
A87: fente_basse | B87: Fente basse (posture du croissant) | C87: Nouveau | G87: yoga | H87: jambes, fessiers | I87: mobilite | J87: 1 | K87: non | L87: aucun | M87: 60 s | N87: 1. Mains sur la cuisse, 30 s par côté (60 s) 2. Bras levés, 30 s par côté (60 s) 3. 45 s par côté (90 s) | O87: Fléchisseurs de hanche, Quadriceps | P87: Grand fessier, Épaules (avant) | Q87: 2.3 (code 02150, Yoga hatha) | R87: Genou arrière posé au sol, pied avant devant toi. Avance doucement le bassin vers l'avant. Lève les bras si l'équilibre le permet. Change de côté à mi-temps. | S87: Une serviette pliée sous le genou arrière rend la posture plus confortable. | T87: Respire lentement, relâche à chaque expiration. | U87: Cambrer le bas du dos. Genou avant qui dépasse la cheville. | V87: Yoga Journal, Low Lunge : https://www.yogajournal.com/poses/low-lunge/ | W87: Yoga : posture du croissant de lune (Anjaneyasana) (français) https://www.youtube.com/watch?v=A5wGqQ21l2o
A88: pigeon | B88: Pigeon (version au sol) | C88: Nouveau | G88: yoga | H88: fessiers | I88: mobilite, detente | J88: 2 | K88: non | L88: aucun | M88: 60 s | N88: 1. Buste redressé, 30 s par côté (60 s) 2. Buste allongé vers l'avant (60 s) 3. 45 s par côté (90 s) | O88: Grand fessier, Moyen fessier | P88: Fléchisseurs de hanche | Q88: 2.3 (code 02150, Yoga hatha) | R88: À quatre pattes, avance un genou derrière le poignet du même côté. Allonge l'autre jambe vers l'arrière, bassin le plus droit possible. Reste buste droit ou allonge-le vers l'avant. Change de côté à mi-temps. | S88: Si le genou plié se plaint, fais plutôt l'étirement des fessiers en « 4 » sur le dos. | T88: Respire lentement dans la hanche étirée. | U88: Bassin qui bascule sur le côté. Forcer sur le genou. | V88: Yoga Journal, Sleeping Pigeon Pose : https://www.yogajournal.com/article/yogapedia/master-sleeping-pigeon-pose-4-steps/ | W88: Posture du pigeon (Yoga by Decathlon) (français) https://www.youtube.com/watch?v=YqNO0ImMtEY
A89: papillon | B89: Papillon | C89: Nouveau | G89: yoga | H89: jambes, fessiers | I89: mobilite, detente | J89: 1 | K89: non | L89: aucun | M89: 45 s | N89: 1. 30 s (30 s) 2. 45 s (45 s) 3. 1 min, buste incliné (60 s) | O89: Adducteurs | P89: Bas du dos (lombaires) | Q89: 2.3 (code 02150, Yoga hatha) | R89: Assis, plantes des pieds l'une contre l'autre, genoux ouverts. Tiens tes pieds et grandis-toi. Laisse les genoux descendre d'eux-mêmes, sans appuyer dessus. | S89: Assieds-toi sur un coussin si le dos s'arrondit. | T89: Respire lentement, relâche à chaque expiration. | U89: Appuyer sur les genoux. Dos arrondi. | V89: Yoga Journal, Bound Angle Pose : https://www.yogajournal.com/poses/bound-angle-pose-2/ | W89: Posture de yoga du papillon, Baddha Konasana (français) https://www.youtube.com/watch?v=53WnXeu_Yuw
... A94: quadriceps_debout | B94: Étirement des quadriceps debout | C94: Nouveau | G94: etirement | H94: jambes | I94: mobilite | J94: 1 | K94: non | L94: aucun | M94: 60 s | N94: 1. 20 s par côté (40 s) 2. 30 s par côté (60 s) | O94: Quadriceps | P94: Fléchisseurs de hanche | Q94: 2.3 (code 02101, Étirements doux) | R94: Debout, une main sur un appui (mur, dossier de chaise). Attrape ta cheville et ramène le talon vers la fesse. Genoux côte à côte, bassin légèrement rentré. Change de côté. | S94: Utilise une serviette autour de la cheville si tu ne l'attrapes pas. | T94: Respire lentement pendant le maintien. | U94: Genou qui part vers l'avant ou sur le côté. Cambrer le dos. | V94: free-exercise-db (domaine public), fiche Quad Stretch : https://github.com/yuhonas/free-exercise-db/blob/main/exercises/Quad_Stretch.json NHS, Flexibility exercises : https://www.nhs.uk/live-well/exercise/flexibility-exercises/ | W94: Étirement des quadriceps en position debout (Masseo) (français) https://www.youtube.com/watch?v=4c5oLJxm2Nk
A95: etirement_lateral | B95: Étirement latéral debout | C95: Nouveau | G95: etirement | H95: dos, abdos | I95: mobilite | J95: 1 | K95: non | L95: aucun | M95: 40 s | N95: 1. 15 s par côté (30 s) 2. 20 s par côté (40 s) | O95: Obliques, Grand dorsal | Q95: 2.3 (code 02101, Étirements doux) | R95: Debout, pieds largeur de hanches. Lève un bras au-dessus de la tête et penche-toi doucement de l'autre côté. Reviens au centre et change de côté. | S95: Penche-toi sur le côté, pas vers l'avant. | T95: Inspire en levant le bras, expire en t'inclinant. | U95: Tourner le buste. Hausser l'épaule. | V95: free-exercise-db (domaine public), fiche Standing Lateral Stretch : https://github.com/yuhonas/free-exercise-db/blob/main/exercises/Standing_Lateral_Stretch.json | W95: Étirement latéral debout (français) https://www.youtube.com/watch?v=ML6zsqBPmPg
A96: epaule_bras_croise | B96: Étirement de l'épaule, bras croisé | C96: Nouveau | G96: etirement | H96: epaules | I96: mobilite | J96: 1 | K96: non | L96: aucun | M96: 40 s | N96: 1. 20 s par côté (40 s) 2. 30 s par côté (60 s) | O96: Épaules (arrière) | P96: Haut du dos (rhomboïdes) | Q96: 2.3 (code 02101, Étirements doux) | R96: Amène un bras tendu devant la poitrine. Avec l'autre main, rapproche-le doucement du corps, au-dessus du coude. Épaules basses. Change de côté. | S96: Appuie au-dessus du coude, jamais dessus. | T96: Respire calmement. | U96: Hausser l'épaule étirée. Tourner le buste. | V96: free-exercise-db (domaine public), fiche Shoulder Stretch : https://github.com/yuhonas/free-exercise-db/blob/main/exercises/Shoulder_Stretch.json | W96: Étirement épaule : technique bras croisé devant la poitrine (français) https://www.youtube.com/watch?v=mlUh1XQikKM
A97: triceps_etirement | B97: Étirement des triceps | C97: Nouveau | G97: etirement | H97: bras | I97: mobilite | J97: 1 | K97: non | L97: aucun | M97: 40 s | N97: 1. 20 s par côté (40 s) 2. 30 s par côté (60 s) | O97: Triceps | P97: Grand dorsal | Q97: 2.3 (code 02101, Étirements doux) | R97: Lève un bras et plie le coude pour poser la main entre les omoplates. Avec l'autre main, pousse doucement le coude vers l'arrière. Change de côté. | S97: Reste dans une amplitude confortable pour l'épaule. | T97: Respire calmement. | U97: Cambrer le dos. Pencher la tête vers l'avant. | V97: free-exercise-db (domaine public), fiche Triceps Stretch : https://github.com/yuhonas/free-exercise-db/blob/main/exercises/Triceps_Stretch.json | W97: Étirement triceps : technique bras derrière la tête (français) https://www.youtube.com/watch?v=V8nA6t_r8JM
A98: torsion_assise | B98: Torsion assise | C98: Nouveau | G98: etirement | H98: dos | I98: mobilite | J98: 1 | K98: non | L98: aucun | M98: 40 s | N98: 1. 20 s par côté (40 s) 2. 30 s par côté (60 s) | O98: Obliques, Bas du dos (lombaires) | P98: Grand fessier | Q98: 2.3 (code 02101, Étirements doux) | R98: Assis, une jambe tendue, l'autre pied posé à l'extérieur du genou. Grandis-toi, puis tourne le buste vers le genou plié. Coude contre le genou, regard derrière toi. Change de côté. | S98: Grandis-toi à chaque inspiration, tourne un peu à chaque expiration. | T98: Inspire en te grandissant, expire en tournant. | U98: Dos arrondi. Forcer avec le bras. | V98: free-exercise-db (domaine public), fiche Spinal Stretch : https://github.com/yuhonas/free-exercise-db/blob/main/exercises/Spinal_Stretch.json | W98: 1 minute de yoga par jour : torsion assise (français) https://www.youtube.com/watch?v=gsp1AZcEn54
A99: genoux_poitrine | B99: Genoux à la poitrine | C99: Nouveau | G99: etirement | H99: dos | I99: mobilite, detente | J99: 1 | K99: non | L99: aucun | M99: 40 s | N99: 1. Une jambe à la fois (40 s) 2. Deux jambes, léger balancement (40 s) | O99: Bas du dos (lombaires) | P99: Grand fessier | Q99: 2.3 (code 02101, Étirements doux) | R99: Allongé sur le dos. Ramène les genoux vers la poitrine, mains sous les genoux. Balance-toi doucement de gauche à droite si c'est agréable. | T99: Respire lentement dans le ventre. | U99: Décoller la tête. Tirer fort sur les genoux. | V99: free-exercise-db (domaine public), fiche Hug Knees To Chest : https://github.com/yuhonas/free-exercise-db/blob/main/exercises/Hug_Knees_To_Chest.json NHS, Flexibility exercises : https://www.nhs.uk/live-well/exercise/flexibility-exercises/ | W99: Un étirement pour détendre les lombaires (français) https://www.youtube.com/watch?v=KCiEleLODc8
A100: coherence_cardiaque | B100: Respiration lente (6 cycles par minute) | C100: Nouveau | G100: meditation | I100: detente | J100: 1 | K100: non | L100: aucun | M100: 180 s | N100: 1. 3 min (180 s) 2. 5 min (300 s) | O100: Diaphragme | Q100: 1 (code 07075, Méditation) | R100: Assis, dos droit, pieds au sol. Inspire par le nez pendant 5 secondes, puis expire pendant 5 secondes. Garde ce rythme régulier jusqu'à la fin, sans forcer. | S100: Si tu te sens étourdi, reprends une respiration normale. | T100: 5 s d'inspiration, 5 s d'expiration : 6 cycles par minute. | U100: Gonfler la poitrine plutôt que le ventre. Forcer l'inspiration. | V100: Respiration lente autour de 6 cycles par minute, revue systématique (Université de Berne) : https://boris.unibe.ch/193198 | W100: Cohérence cardiaque 5:5, 5 minutes de respiration guidée (français) https://www.youtube.com/watch?v=vs_8iqpGoEM
A101: respiration_carree | B101: Respiration carrée | C101: Nouveau | G101: meditation | I101: detente | J101: 1 | K101: non | L101: aucun | M101: 120 s | N101: 1. 2 min, carré de 3 s (120 s) 2. 3 min, carré de 4 s (180 s) | O101: Diaphragme | Q101: 1 (code 07075, Méditation) | R101: Assis confortablement, expire complètement. Inspire 4 s, retiens 4 s, expire 4 s, retiens 4 s. Recommence en imaginant les quatre côtés d'un carré. | S101: Raccourcis les temps (3 s) si les pauses sont inconfortables. | T101: Quatre temps égaux : inspire, pause, expire, pause. | U101: Contracter les épaules pendant les pauses. Accélérer le compte. | V101: University of Pittsburgh, Box Breathing : https://sova.pitt.edu/box-breathing | W101: Respiration carrée (exercice de 5 min) (français) https://www.youtube.com/watch?v=O6NKXExzkww
A102: meditation_souffle | B102: Méditation : attention au souffle | C102: Nouveau | G102: meditation | I102: detente | J102: 1 | K102: non | L102: aucun | M102: 300 s | N102: 1. 3 min (180 s) 2. 5 min (300 s) 3. 10 min (600 s) | Q102: 1 (code 07075, Méditation) | R102: Assis, dos droit sans raideur, yeux fermés ou regard posé au sol. Porte ton attention sur les sensations du souffle, au niveau des narines ou du ventre. Quand ton esprit s'égare, remarque-le simplement et reviens au souffle. | T102: Respire naturellement, sans chercher à modifier le rythme. | U102: Se reprocher d'avoir des pensées : c'est normal. Contrôler la respiration. | V102: UCLA Mindful, méditations guidées gratuites : https://www.uclahealth.org/uclamindful/guided-meditations NHS Torbay and South Devon, Mindfulness of breath : https://www.torbayandsouthdevon.nhs.uk/uploads/mindfulness-of-breath-instructions.pdf | W102: Méditation guidée courte spéciale débutant, 5 min de pleine conscience (français) https://www.youtube.com/watch?v=VBSelbkOELA
A103: scan_corporel | B103: Méditation : scan corporel | C103: Nouveau | G103: meditation | I103: detente | J103: 1 | K103: non | L103: aucun | M103: 420 s | N103: 1. 5 min (300 s) 2. 7 min (420 s) 3. 10 min (600 s) | Q103: 1 (code 07075, Méditation) | R103: Allongé sur le dos, bras le long du corps, yeux fermés. Promène ton attention des orteils jusqu'au sommet du crâne, zone par zone. Observe chaque sensation sans la juger, puis passe à la zone suivante. | S103: Idéal le soir : si tu t'endors, c'est que ton corps en avait besoin. | T103: Respire naturellement, en imaginant le souffle circuler jusqu'à la zone observée. | U103: Vouloir détendre de force. Aller trop vite d'une zone à l'autre. | V103: Greater Good in Action (UC Berkeley), Body Scan Meditation : https://ggia.berkeley.edu/practice/body_scan_meditation UCLA Mindful, méditations guidées gratuites : https://www.uclahealth.org/uclamindful/guided-meditations | W103: Méditation guidée : balayage corporel 10 min (français) https://www.youtube.com/watch?v=1WAXGcKi9i8
A104: relaxation_progressive | B104: Relaxation musculaire progressive | C104: Nouveau | G104: meditation | I104: detente | J104: 1 | K104: non | L104: aucun | M104: 420 s | N104: 1. 5 min, grandes zones (300 s) 2. 7 min (420 s) 3. 10 min, zone par zone (600 s) | Q104: 1 (code 07075, Méditation) | R104: Allongé ou assis, yeux fermés. Contracte un groupe de muscles 5 secondes (pieds, jambes, ventre, mains, épaules, visage), puis relâche d'un coup. Observe la détente 10 à 15 secondes avant de passer au groupe suivant. | S104: Contracte modérément, jamais jusqu'à la crampe ou la douleur. | T104: Inspire en contractant, expire en relâchant. | U104: Contracter trop fort. Enchaîner sans observer la détente. | V104: University of Rochester, Progressive Muscle Relaxation : https://www.rochester.edu/uhs/ucc/online-screening-resources/progressive-muscle-relaxation | W104: Relaxation musculaire progressive, guidée par Isabelle Soucy, Ph. D. (français) https://www.youtube.com/watch?v=2KSp2uQsEH8
A105: rowing | B105: Rowing assis à l'élastique | C105: Existant, ré-étiqueté | G105: renforcement | H105: dos, bras | I105: renforcer, tonifier | K105: non | L105: elastique | M105: 12 répétitions | N105: (inchangés) | O105: Haut du dos (rhomboïdes), Grand dorsal | P105: Biceps, Épaules (arrière), Trapèzes | Q105: 3.5 (code 02054, Renforcement, 8 à 15 répétitions, résistance variée) | R105: (inchangées) | T105: Expire en tirant, inspire en relâchant. | U105: Se pencher en arrière pour tirer. Hausser les épaules vers les oreilles. | V105: free-exercise-db (domaine public), fiche Seated Cable Rows : https://github.com/yuhonas/free-exercise-db/blob/main/exercises/Seated_Cable_Rows.json | W105: Rowing assis avec élastiques (français) https://www.youtube.com/watch?v=mYdXe92a_EM
A106: pull_apart | B106: Écarté à l'élastique (band pull-apart) | C106: Existant, ré-étiqueté | G106: renforcement | H106: dos, epaules | I106: renforcer, tonifier | K106: non | L106: elastique | M106: 15 répétitions | N106: (inchangés) | O106: Épaules (arrière), Haut du dos (rhomboïdes) | P106: Trapèzes, Coiffe des rotateurs | Q106: 3.5 (code 02054, Renforcement, 8 à 15 répétitions, résistance variée) | R106: (inchangées) | T106: Expire en écartant, inspire en revenant. | U106: Plier les coudes pour s'aider. Cambrer le bas du dos en fin de mouvement. | V106: free-exercise-db (domaine public), fiche Band Pull Apart : https://github.com/yuhonas/free-exercise-db/blob/main/exercises/Band_Pull_Apart.json | W106: Exercice omoplates : band pull apart (français) https://www.youtube.com/watch?v=MSJzslGuutU
A107: pallof | B107: Pallof press (anti-rotation) | C107: Existant, ré-étiqueté | G107: gainage | H107: abdos | I107: renforcer | K107: non | L107: elastique | M107: 40 s | N107: (inchangés) | O107: Obliques, Abdominaux profonds | P107: Abdominaux (grand droit), Moyen fessier | Q107: 2.8 (code 02024, Callisthénie légère (crunchs, planche)) | R107: (inchangées) | T107: Respire calmement pendant que les bras sont tendus, sans bloquer. | U107: Laisser le buste tourner vers l'élastique. Se placer trop près du point d'attache : il n'y a plus de tension. | V107: free-exercise-db (domaine public), fiche Pallof Press : https://github.com/yuhonas/free-exercise-db/blob/main/exercises/Pallof_Press.json | W107: Comment réaliser le Pallof press (français) https://www.youtube.com/watch?v=I4SKLCM9lyo
A108: dead_bug | B108: Dead bug | C108: Existant, ré-étiqueté | G108: gainage | H108: abdos | I108: renforcer | K108: non | L108: aucun | M108: 10 répétitions | N108: (inchangés) | O108: Abdominaux profonds, Abdominaux (grand droit) | P108: Obliques, Fléchisseurs de hanche | Q108: 2.8 (code 02024, Callisthénie légère (crunchs, planche)) | R108: (inchangées) | T108: Expire pendant que le bras et la jambe s'éloignent, inspire en revenant. | U108: Laisser le bas du dos décoller du sol. Aller trop vite et perdre le contrôle. | V108: free-exercise-db (domaine public), fiche Dead Bug : https://github.com/yuhonas/free-exercise-db/blob/main/exercises/Dead_Bug.json | W108: Gainage planche et dead bug : la bonne technique (français) https://www.youtube.com/watch?v=bG17b4f_4bg
A109: bird_dog | B109: Bird-dog | C109: Existant, ré-étiqueté | G109: gainage | H109: dos, abdos | I109: renforcer, mobilite | K109: non | L109: aucun | M109: 10 répétitions | N109: (inchangés) | O109: Bas du dos (lombaires), Grand fessier | P109: Abdominaux profonds, Épaules (avant) | Q109: 2.8 (code 02024, Callisthénie légère (crunchs, planche)) | R109: (inchangées) | T109: Expire en allongeant, inspire en revenant au centre. | U109: Lever la jambe trop haut et creuser le dos. Laisser le bassin basculer sur le côté. | V109: Harvard Health Publishing, Three moves for better spine health (« Big 3 » de Stuart McGill) : https://www.health.harvard.edu/staying-healthy/three-moves-for-better-spine-health | W109: Gainage bird dog : 1 min pour un dos solide (français) https://www.youtube.com/watch?v=l2DXJoi0WYE
A110: planche | B110: Planche | C110: Existant, ré-étiqueté | G110: gainage | H110: abdos, epaules | I110: renforcer, tonifier | K110: non | L110: aucun | M110: 30 s | N110: (inchangés) | O110: Abdominaux (grand droit), Abdominaux profonds | P110: Épaules (avant), Grand fessier, Quadriceps | Q110: 2.8 (code 02024, Callisthénie légère (crunchs, planche)) | R110: (inchangées) | T110: Respire lentement et régulièrement pendant tout le maintien. | U110: Fesses trop hautes ou bassin qui s'affaisse. Bloquer sa respiration. | V110: free-exercise-db (domaine public), fiche Plank : https://github.com/yuhonas/free-exercise-db/blob/main/exercises/Plank.json NHS, Strength exercises : https://www.nhs.uk/live-well/exercise/strength-and-flexibility-exercises/strength-exercises/ | W110: La planche sur les genoux : commence ici pour un gainage parfait (français) https://www.youtube.com/watch?v=ARCrsCnSB-k
A111: squat_chaise | B111: Squat sur chaise | C111: Existant, ré-étiqueté | G111: renforcement | H111: jambes, fessiers | I111: renforcer, tonifier | K111: non | L111: chaise | M111: 10 répétitions | N111: (inchangés) | O111: Quadriceps, Grand fessier | P111: Ischio-jambiers, Adducteurs | Q111: 2.8 (code 02340, Se lever d'une chaise, 6 à 12 par minute) | R111: (inchangées) | T111: Inspire en descendant, expire en te relevant. | U111: Se laisser tomber sur la chaise. Laisser les genoux rentrer vers l'intérieur. | V111: free-exercise-db (domaine public), fiche Chair Squat : https://github.com/yuhonas/free-exercise-db/blob/main/exercises/Chair_Squat.json NHS, Strength exercises : https://www.nhs.uk/live-well/exercise/strength-and-flexibility-exercises/strength-exercises/ | W111: Squat sur chaise (français) https://www.youtube.com/watch?v=bAiHLkX0iWo
A112: pont | B112: Pont fessier | C112: Existant, ré-étiqueté | G112: renforcement | H112: fessiers, jambes | I112: renforcer, tonifier | K112: non | L112: aucun | M112: 12 répétitions | N112: (inchangés) | O112: Grand fessier | P112: Ischio-jambiers, Bas du dos (lombaires) | Q112: 3 (code 02056, Renforcement au poids du corps, général) | R112: (inchangées) | T112: Expire en montant le bassin, inspire en redescendant. | U112: Cambrer le dos en haut au lieu de serrer les fessiers. Pousser sur la pointe des pieds. | V112: free-exercise-db (domaine public), fiche Butt Lift Bridge : https://github.com/yuhonas/free-exercise-db/blob/main/exercises/Butt_Lift_Bridge.json | W112: Comment faire un pont fessier (français) https://www.youtube.com/watch?v=9Wma4mC8wpw
A113: marche_laterale | B113: Marche latérale à l'élastique | C113: Existant, ré-étiqueté | G113: renforcement | H113: fessiers | I113: renforcer, tonifier | K113: non | L113: elastique | M113: 40 s | N113: (inchangés) | O113: Moyen fessier | P113: Grand fessier, Quadriceps | Q113: 3.5 (code 02054, Renforcement, 8 à 15 répétitions, résistance variée) | R113: (inchangées) | T113: Respiration libre et régulière. | U113: Laisser les pieds se toucher : l'élastique se détend. Balancer le buste d'un côté à l'autre. | V113: free-exercise-db (domaine public), fiche Monster Walk : https://github.com/yuhonas/free-exercise-db/blob/main/exercises/Monster_Walk.json | W113: Banded Lateral Walk (anglais) https://www.youtube.com/watch?v=mZ23K1ulW2A
A114: ext_hanche | B114: Extension de hanche à quatre pattes | C114: Existant, ré-étiqueté | G114: renforcement | H114: fessiers | I114: renforcer, tonifier | K114: non | L114: aucun | M114: 12 répétitions | N114: (inchangés) | O114: Grand fessier | P114: Ischio-jambiers, Bas du dos (lombaires) | Q114: 3 (code 02056, Renforcement au poids du corps, général) | R114: (inchangées) | T114: Expire en poussant le talon vers le plafond, inspire en revenant. | U114: Monter trop haut et creuser le dos. Tourner le bassin vers l'extérieur. | V114: free-exercise-db (domaine public), fiche Glute Kickback : https://github.com/yuhonas/free-exercise-db/blob/main/exercises/Glute_Kickback.json | W114: Extension de la hanche, genou plié (français) https://www.youtube.com/watch?v=xwTFt_yWEkI
A115: planche_laterale | B115: Planche latérale | C115: Existant, ré-étiqueté | G115: gainage | H115: abdos | I115: renforcer, tonifier | K115: non | L115: aucun | M115: 30 s | N115: (inchangés) | O115: Obliques | P115: Abdominaux profonds, Moyen fessier, Épaules (côté) | Q115: 2.8 (code 02024, Callisthénie légère (crunchs, planche)) | R115: (inchangées) | T115: Respire calmement, sans bloquer. | U115: Laisser le bassin descendre. Pencher le buste vers l'avant. | V115: Harvard Health Publishing, Three moves for better spine health (« Big 3 » de Stuart McGill) : https://www.health.harvard.edu/staying-healthy/three-moves-for-better-spine-health free-exercise-db (domaine public), fiche Side Bridge : https://github.com/yuhonas/free-exercise-db/blob/main/exercises/Side_Bridge.json | W115: Comment bien faire son gainage latéral ? Tutoriel et progression par kiné (français) https://www.youtube.com/watch?v=_H9lCamSHR0
A116: respiration | B116: Respiration costale | C116: Existant, ré-étiqueté | G116: meditation | H116: abdos | I116: detente | K116: non | L116: aucun | M116: 60 s | N116: (inchangés) | O116: Diaphragme | P116: Abdominaux profonds | Q116: 1 (code 07075, Méditation) | R116: (inchangées) | T116: Inspire 3 à 4 s par le nez, expire 5 à 6 s par la bouche. | U116: Monter les épaules en inspirant. Forcer l'inspiration. | V116: Respiration lente autour de 6 cycles par minute, revue systématique (Université de Berne) : https://boris.unibe.ch/193198 | W116: Comment maîtriser la respiration latérale costale en Pilates ? (français) https://www.youtube.com/watch?v=3Bb4ytM0ARA
... A118: chat_vache | B118: Chat-vache | C118: Existant, ré-étiqueté | G118: yoga | H118: dos | I118: mobilite, detente | K118: non | L118: aucun | M118: 45 s | N118: (inchangés) | O118: Bas du dos (lombaires) | P118: Abdominaux profonds, Trapèzes | Q118: 2.3 (code 02150, Yoga hatha) | R118: (inchangées) | T118: Inspire en creusant, expire en arrondissant. | U118: Forcer la cambrure. Plier les coudes. | V118: free-exercise-db (domaine public), fiche Cat Stretch : https://github.com/yuhonas/free-exercise-db/blob/main/exercises/Cat_Stretch.json NHS, Flexibility exercises : https://www.nhs.uk/live-well/exercise/flexibility-exercises/ | W118: Chat-vache : soulage ton dos en 3 min (yoga débutant) (français) https://www.youtube.com/watch?v=Sf0h4chQzis
A119: omoplates | B119: Rapprochement des omoplates | C119: Existant, ré-étiqueté | G119: renforcement | H119: dos | I119: mobilite | K119: non | L119: aucun | M119: 45 s | N119: (inchangés) | O119: Haut du dos (rhomboïdes), Trapèzes | Q119: 3.5 (code 02030, Callisthénie légère à modérée (exercices du dos, se relever du sol)) | R119: (inchangées) | T119: Expire en serrant, inspire en relâchant. | U119: Hausser les épaules. Cambrer le bas du dos. | V119: free-exercise-db (domaine public), fiche Upper Back Stretch : https://github.com/yuhonas/free-exercise-db/blob/main/exercises/Upper_Back_Stretch.json | W119: Exercice épaule : rapprocher les omoplates (français) https://www.youtube.com/watch?v=pdI4HS138tc
A120: wall_slides | B120: Glissés de bras au mur | C120: Existant, ré-étiqueté | G120: etirement | H120: epaules, dos | I120: mobilite | K120: non | L120: mur | M120: 45 s | N120: (inchangés) | O120: Trapèzes, Épaules (côté) | P120: Coiffe des rotateurs, Haut du dos (rhomboïdes) | Q120: 2.3 (code 02101, Étirements doux) | R120: (inchangées) | T120: Inspire en montant, expire en redescendant. | U120: Décoller le bas du dos du mur. Monter les épaules vers les oreilles. | V120: NHS, Flexibility exercises : https://www.nhs.uk/live-well/exercise/flexibility-exercises/ | W120: Wall slide exercice (Nxt Generation Physio) (français) https://www.youtube.com/watch?v=K8TMa3-E2Is
A121: ext_thoracique | B121: Extension thoracique sur chaise | C121: Existant, ré-étiqueté | G121: etirement | H121: dos | I121: mobilite | K121: non | L121: chaise | M121: 45 s | N121: (inchangés) | O121: Haut du dos (rhomboïdes), Bas du dos (lombaires) | P121: Pectoraux | Q121: 2.3 (code 02101, Étirements doux) | R121: (inchangées) | T121: Inspire en ouvrant la poitrine, expire en revenant. | U121: Cambrer le bas du dos au lieu du haut. Pousser la tête en arrière. | V121: free-exercise-db (domaine public), fiche Chair Upper Body Stretch : https://github.com/yuhonas/free-exercise-db/blob/main/exercises/Chair_Upper_Body_Stretch.json | W121: Thoracic Extension Over a Chair (anglais) https://www.youtube.com/watch?v=4ZqOMX-18O0
A122: chin_tuck | B122: Menton rentré | C122: Existant, ré-étiqueté | G122: etirement | H122: dos | I122: mobilite | K122: non | L122: aucun | M122: 45 s | N122: (inchangés) | O122: Cou | Q122: 2.3 (code 02101, Étirements doux) | R122: (inchangées) | T122: Respiration libre, sans bloquer pendant le maintien. | U122: Baisser le menton vers la poitrine au lieu de le reculer. Contracter les épaules. | V122: NHS, Flexibility exercises : https://www.nhs.uk/live-well/exercise/flexibility-exercises/ | W122: Chin Tucks (Cervical Retractions) (anglais) https://www.youtube.com/watch?v=tQYo15dpKdM
A123: pecs_porte | B123: Étirement des pectoraux (porte) | C123: Existant, ré-étiqueté | G123: etirement | H123: bras, epaules | I123: mobilite, detente | K123: non | L123: mur | M123: 60 s | N123: (inchangés) | O123: Pectoraux | P123: Épaules (avant) | Q123: 2.3 (code 02101, Étirements doux) | R123: (inchangées) | T123: Expire en avançant le buste, puis respire calmement. | U123: Monter le coude au-dessus de l'épaule. Cambrer le dos pour gagner de l'amplitude. | V123: free-exercise-db (domaine public), fiche Chest And Front Of Shoulder Stretch : https://github.com/yuhonas/free-exercise-db/blob/main/exercises/Chest_And_Front_Of_Shoulder_Stretch.json | W123: Étirement du grand et du petit pectoral (Masseo) (français) https://www.youtube.com/watch?v=6pIDnFHUK8E
A124: trapezes | B124: Étirement des trapèzes | C124: Existant, ré-étiqueté | G124: etirement | H124: dos, epaules | I124: mobilite, detente | K124: non | L124: aucun | M124: 60 s | N124: (inchangés) | O124: Trapèzes, Cou | Q124: 2.3 (code 02101, Étirements doux) | R124: (inchangées) | T124: Expire en relâchant l'épaule opposée vers le bas. | U124: Tirer sur la tête avec la main. Hausser l'épaule du côté étiré. | V124: free-exercise-db (domaine public), fiche Side Neck Stretch : https://github.com/yuhonas/free-exercise-db/blob/main/exercises/Side_Neck_Stretch.json NHS, Flexibility exercises : https://www.nhs.uk/live-well/exercise/flexibility-exercises/ | W124: Étirement du trapèze supérieur (Masseo) (français) https://www.youtube.com/watch?v=vfoWMKhx4v4
A125: enfant | B125: Posture de l'enfant | C125: Existant, ré-étiqueté | G125: yoga | H125: dos | I125: mobilite, detente | K125: non | L125: aucun | M125: 30 s | N125: (inchangés) | O125: Bas du dos (lombaires) | P125: Grand dorsal, Grand fessier | Q125: 2.3 (code 02150, Yoga hatha) | R125: (inchangées) | T125: Respire dans le dos : il se gonfle à l'inspiration. | U125: Forcer les fesses vers les talons si les genoux tirent. Retenir sa respiration. | V125: free-exercise-db (domaine public), fiche Childs Pose : https://github.com/yuhonas/free-exercise-db/blob/main/exercises/Childs_Pose.json | W125: Yoga : posture de l'enfant, Balasana (français) https://www.youtube.com/watch?v=8kGL8IghPbo
A126: flechisseurs | B126: Étirement des fléchisseurs de hanche | C126: Existant, ré-étiqueté | G126: etirement | H126: jambes, fessiers | I126: mobilite | K126: non | L126: aucun | M126: 60 s | N126: (inchangés) | O126: Fléchisseurs de hanche | P126: Quadriceps | Q126: 2.3 (code 02101, Étirements doux) | R126: (inchangées) | T126: Expire en avançant le bassin, puis respire calmement. | U126: Cambrer le bas du dos. Avancer le genou avant au-delà des orteils. | V126: free-exercise-db (domaine public), fiche Kneeling Hip Flexor : https://github.com/yuhonas/free-exercise-db/blob/main/exercises/Kneeling_Hip_Flexor.json NHS, Flexibility exercises : https://www.nhs.uk/live-well/exercise/flexibility-exercises/ | W126: Étirement psoas : technique en fente genou au sol (français) https://www.youtube.com/watch?v=5M6zv6hGskQ
A127: ischios | B127: Étirement des ischio-jambiers | C127: Existant, ré-étiqueté | G127: etirement | H127: jambes | I127: mobilite | K127: non | L127: aucun | M127: 60 s | N127: (inchangés) | O127: Ischio-jambiers | P127: Mollets | Q127: 2.3 (code 02101, Étirements doux) | R127: (inchangées) | T127: Expire en rapprochant doucement la jambe. | U127: Verrouiller le genou à tout prix. Décoller les fesses du sol. | V127: free-exercise-db (domaine public), fiche Hamstring Stretch : https://github.com/yuhonas/free-exercise-db/blob/main/exercises/Hamstring_Stretch.json | W127: Étirement des ischio-jambiers en position allongée (français) https://www.youtube.com/watch?v=WTZQYMpSNJk
A128: fessiers_4 | B128: Étirement des fessiers en « 4 » | C128: Existant, ré-étiqueté | G128: etirement | H128: fessiers | I128: mobilite, detente | K128: non | L128: aucun | M128: 60 s | N128: (inchangés) | O128: Grand fessier, Moyen fessier | Q128: 2.3 (code 02101, Étirements doux) | R128: (inchangées) | T128: Expire en rapprochant la jambe, puis respire calmement. | U128: Tirer sur la tête et le cou pour attraper la jambe. Forcer sur le genou croisé. | V128: free-exercise-db (domaine public), fiche Ankle On The Knee : https://github.com/yuhonas/free-exercise-db/blob/main/exercises/Ankle_On_The_Knee.json NHS, Flexibility exercises : https://www.nhs.uk/live-well/exercise/flexibility-exercises/ | W128: Étirement du muscle pyramidal en position allongée (français) https://www.youtube.com/watch?v=_tvE9m9kkxM
A129: mollets | B129: Étirement des mollets | C129: Existant, ré-étiqueté | G129: etirement | H129: jambes | I129: mobilite | K129: non | L129: mur | M129: 60 s | N129: (inchangés) | O129: Mollets | Q129: 2.3 (code 02101, Étirements doux) | R129: (inchangées) | T129: Respiration lente pendant le maintien. | U129: Décoller le talon arrière. Tourner le pied arrière vers l'extérieur. | V129: free-exercise-db (domaine public), fiche Calf Stretch Hands Against Wall : https://github.com/yuhonas/free-exercise-db/blob/main/exercises/Calf_Stretch_Hands_Against_Wall.json NHS, Flexibility exercises : https://www.nhs.uk/live-well/exercise/flexibility-exercises/ | W129: Étirement mollets : technique debout contre le mur (français) https://www.youtube.com/watch?v=zzNI5vxssTI
A130: glissement_talon | B130: Glissement de talon | C130: Existant, ré-étiqueté | G130: pilates | H130: abdos | I130: renforcer | K130: non | L130: aucun | M130: 10 répétitions | N130: (inchangés) | O130: Abdominaux profonds | P130: Abdominaux (grand droit), Fléchisseurs de hanche | Q130: 1.8 (code 02103, Pilates au sol) | R130: (inchangées) | T130: Expire en faisant glisser le talon, inspire en revenant. | U130: Creuser le dos quand la jambe s'allonge. Aller trop vite. | V130: free-exercise-db (domaine public), fiche Flat Bench Lying Leg Raise : https://github.com/yuhonas/free-exercise-db/blob/main/exercises/Flat_Bench_Lying_Leg_Raise.json | W130: Core Exercise: Heel Slide (anglais) https://www.youtube.com/watch?v=6-anByqnKp8
A131: planche_inclinee | B131: Planche inclinée, mains en appui | C131: Existant, ré-étiqueté | G131: gainage | H131: abdos, epaules | I131: renforcer | K131: non | L131: chaise | M131: 30 s | N131: (inchangés) | O131: Abdominaux (grand droit), Abdominaux profonds | P131: Épaules (avant), Pectoraux | Q131: 2.8 (code 02024, Callisthénie légère (crunchs, planche)) | R131: (inchangées) | T131: Respire lentement pendant tout le maintien. | U131: Bassin qui s'affaisse. Support instable qui glisse. | V131: free-exercise-db (domaine public), fiche Plank : https://github.com/yuhonas/free-exercise-db/blob/main/exercises/Plank.json | W131: Gainage à l'aide d'une chaise (français) https://www.youtube.com/watch?v=jLcQfXPMHXY
A132: pallof_genoux | B132: Pallof press à genoux | C132: Existant, ré-étiqueté | G132: gainage | H132: abdos | I132: renforcer | K132: non | L132: elastique | M132: 40 s | N132: (inchangés) | O132: Obliques, Abdominaux profonds | P132: Grand fessier | Q132: 2.8 (code 02024, Callisthénie légère (crunchs, planche)) | R132: (inchangées) | T132: Respire calmement bras tendus, sans bloquer. | U132: Laisser le buste tourner. S'asseoir sur les talons. | V132: free-exercise-db (domaine public), fiche Pallof Press : https://github.com/yuhonas/free-exercise-db/blob/main/exercises/Pallof_Press.json | W132: How to do a Half Kneeling Pallof Press (anglais) https://www.youtube.com/watch?v=LpBNsIv2olo
A133: rowing_debout | B133: Rowing debout à l'élastique | C133: Existant, ré-étiqueté | G133: renforcement | H133: dos, bras | I133: renforcer, tonifier | K133: non | L133: elastique | M133: 12 répétitions | N133: (inchangés) | O133: Haut du dos (rhomboïdes), Grand dorsal | P133: Biceps, Épaules (arrière) | Q133: 3.5 (code 02054, Renforcement, 8 à 15 répétitions, résistance variée) | R133: (inchangées) | T133: Expire en tirant, inspire en relâchant. | U133: Balancer le buste. Tirer avec les mains plutôt qu'avec les coudes. | V133: free-exercise-db (domaine public), fiche Seated Cable Rows : https://github.com/yuhonas/free-exercise-db/blob/main/exercises/Seated_Cable_Rows.json | W133: Exercice dos à la bande élastique : tirage horizontal debout (français) https://www.youtube.com/watch?v=OcYrtl3ZAMs
A134: face_pull_bas | B134: Tirage coudes écartés à l'élastique | C134: Existant, ré-étiqueté | G134: renforcement | H134: epaules, dos | I134: renforcer | K134: non | L134: elastique | M134: 12 répétitions | N134: (inchangés) | O134: Épaules (arrière), Haut du dos (rhomboïdes) | P134: Coiffe des rotateurs, Trapèzes | Q134: 3.5 (code 02054, Renforcement, 8 à 15 répétitions, résistance variée) | R134: (inchangées) | T134: Expire en tirant, inspire en revenant. | U134: Hausser les épaules. Cambrer le dos pour finir le tirage. | V134: free-exercise-db (domaine public), fiche Reverse Flyes : https://github.com/yuhonas/free-exercise-db/blob/main/exercises/Reverse_Flyes.json | W134: Resistance band face pull : exercice à l'élastique pour l'arrière des épaules (français) https://www.youtube.com/watch?v=i-hVYySziaU
A135: rotation_externe | B135: Rotation externe d'épaule à l'élastique | C135: Existant, ré-étiqueté | G135: renforcement | H135: epaules | I135: renforcer | K135: non | L135: elastique | M135: 12 répétitions | N135: (inchangés) | O135: Coiffe des rotateurs | P135: Épaules (arrière) | Q135: 3.5 (code 02054, Renforcement, 8 à 15 répétitions, résistance variée) | R135: (inchangées) | T135: Expire en écartant l'avant-bras, inspire en revenant. | U135: Décoller le coude du corps. Élastique trop dur : le mouvement devient saccadé. | V135: free-exercise-db (domaine public), fiche External Rotation with Band : https://github.com/yuhonas/free-exercise-db/blob/main/exercises/External_Rotation_with_Band.json | W135: Rotation externe d'épaule (coude au corps) (français) https://www.youtube.com/watch?v=zUP5qcl9AeA
A136: elevation_laterale | B136: Élévation latérale à l'élastique | C136: Existant, ré-étiqueté | G136: renforcement | H136: epaules | I136: renforcer, tonifier | K136: non | L136: elastique | M136: 12 répétitions | N136: (inchangés) | O136: Épaules (côté) | P136: Trapèzes | Q136: 3.5 (code 02054, Renforcement, 8 à 15 répétitions, résistance variée) | R136: (inchangées) | T136: Expire en montant, inspire en descendant. | U136: Monter au-dessus des épaules. Prendre de l'élan avec le buste. | V136: free-exercise-db (domaine public), fiche Lateral Raise - With Bands : https://github.com/yuhonas/free-exercise-db/blob/main/exercises/Lateral_Raise_-_With_Bands.json | W136: Élévations latérales à l'élastique pour muscler les épaules (français) https://www.youtube.com/watch?v=zz9D2QulpBs
A137: curl_biceps | B137: Curl des biceps à l'élastique | C137: Existant, ré-étiqueté | G137: renforcement | H137: bras | I137: renforcer, tonifier | K137: non | L137: elastique | M137: 12 répétitions | N137: (inchangés) | O137: Biceps | P137: Avant-bras | Q137: 3.5 (code 02054, Renforcement, 8 à 15 répétitions, résistance variée) | R137: (inchangées) | T137: Expire en pliant les coudes, inspire en redescendant. | U137: Avancer les coudes. Se cambrer pour finir la montée. | V137: free-exercise-db (domaine public), fiche Close-Grip EZ-Bar Curl with Band : https://github.com/yuhonas/free-exercise-db/blob/main/exercises/Close-Grip_EZ-Bar_Curl_with_Band.json | W137: Curl biceps élastique (français) https://www.youtube.com/watch?v=L2QhFSJ-Jb4
A138: triceps_elastique | B138: Extension des triceps à l'élastique | C138: Existant, ré-étiqueté | G138: renforcement | H138: bras | I138: renforcer, tonifier | K138: non | L138: elastique | M138: 12 répétitions | N138: (inchangés) | O138: Triceps | Q138: 3.5 (code 02054, Renforcement, 8 à 15 répétitions, résistance variée) | R138: (inchangées) | T138: Expire en tendant les bras, inspire en revenant. | U138: Écarter les coudes du corps. Se pencher en avant pour pousser. | V138: free-exercise-db (domaine public), fiche Triceps Pushdown : https://github.com/yuhonas/free-exercise-db/blob/main/exercises/Triceps_Pushdown.json | W138: Triceps extension élastique (français) https://www.youtube.com/watch?v=IH3w7O5UWKU
A139: clamshell | B139: Clamshell (coquillage) | C139: Existant, ré-étiqueté | G139: renforcement | H139: fessiers | I139: renforcer, tonifier | K139: non | L139: aucun | M139: 15 répétitions | N139: (inchangés) | O139: Moyen fessier | P139: Grand fessier | Q139: 3 (code 02056, Renforcement au poids du corps, général) | R139: (inchangées) | T139: Expire en ouvrant le genou, inspire en refermant. | U139: Rouler le bassin vers l'arrière. Décoller les pieds l'un de l'autre. | W139: Bien exécuter l'exercice du clamshell (français) https://www.youtube.com/watch?v=0e4oPtPbqvQ
...

Sheet Entraînements
A1: Identifiant | B1: Titre | C1: Type | D1: Validé | E1: Commentaire | F1: Niveau | G1: Zones | H1: Durée (min) | I1: Calories (estimation, poids du mode d'emploi) | J1: Tours | K1: Pause (s) | L1: Sauts | M1: Matériel | N1: Description | O1: Contenu
A2: prog_mobilite_s1 | B2: Mobilité douce | C2: Jour de programme | F2: 1 | G2: corps_entier | H2: 5 | I2: =ROUND(8.7*'Mode d''emploi'!$B$20/60,0) -> 9 | J2: 1 | K2: 10 | L2: non | M2: aucun | N2: Une séance courte pour délier le dos, les hanches et les épaules entre deux renforcements. | O2: Corps : Chat-vache Corps : Cercles de hanches Corps : Livre ouvert (rotation du haut du dos) Corps : Le plus grand étirement du monde Corps : Posture de l'enfant
A3: prog_mobilite_s2 | B3: Mobilité du dos et des hanches | C3: Jour de programme | F3: 1 | G3: corps_entier | H3: 6 | I3: =ROUND(11.8*'Mode d''emploi'!$B$20/60,0) -> 12 | J3: 1 | K3: 10 | L3: non | M3: aucun | N3: Mobilité active pour récupérer et bouger mieux. | O3: Corps : Chat-vache Corps : Cercles de bras Corps : Rotations du buste Corps : Le plus grand étirement du monde Corps : Fente basse (posture du croissant) Corps : Posture de l'enfant
A4: prog_mobilite_s3 | B4: Mobilité et salutation au soleil | C4: Jour de programme | F4: 1 | G4: corps_entier | H4: 7 | I4: =ROUND(15.3*'Mode d''emploi'!$B$20/60,0) -> 15 | J4: 1 | K4: 10 | L4: non | M4: aucun | N4: Mobilité puis deux salutations au soleil en douceur. | O4: Corps : Chat-vache Corps : Cercles de hanches Corps : Salutation au soleil (version douce) Corps : Le plus grand étirement du monde Corps : Sphinx Corps : Torsion allongée
A5: prog_mobilite_s4 | B5: Mobilité complète | C5: Jour de programme | F5: 1 | G5: corps_entier | H5: 9 | I5: =ROUND(20.7*'Mode d''emploi'!$B$20/60,0) -> 21 | J5: 1 | K5: 10 | L5: non | M5: aucun | N5: Une séance de mobilité plus longue pour finir le mois en souplesse. | O5: Corps : Chat-vache Corps : Cercles de bras Corps : Salutation au soleil (version douce) Corps : Le plus grand étirement du monde Corps : Fente basse (posture du croissant) Corps : Pigeon (version au sol) Corps : Torsion allongée
A6: prog_recup_s1 | B6: Récupération : étirements | C6: Jour de programme | F6: 1 | G6: corps_entier | H6: 7 | I6: =ROUND(13*'Mode d''emploi'!$B$20/60,0) -> 13 | J6: 1 | K6: 10 | L6: non | M6: aucun | N6: Étirements doux de tout le corps pour finir la semaine. | O6: Corps : Genoux à la poitrine Corps : Étirement des fessiers en « 4 » Corps : Étirement des ischio-jambiers Corps : Torsion allongée Corps : Posture de l'enfant Corps : Respiration costale
A7: prog_recup_s2 | B7: Récupération : yoga doux | C7: Jour de programme | F7: 1 | G7: corps_entier | H7: 9 | I7: =ROUND(13.6*'Mode d''emploi'!$B$20/60,0) -> 14 | J7: 1 | K7: 10 | L7: non | M7: aucun | N7: Postures de yoga au sol et respiration lente. | O7: Corps : Chat-vache Corps : Sphinx Corps : Posture de l'enfant Corps : Papillon Corps : Torsion allongée Corps : Respiration lente (6 cycles par minute)
A8: prog_recup_s3 | B8: Récupération : hanches et dos | C8: Jour de programme | F8: 1 | G8: corps_entier | H8: 9 | I8: =ROUND(14.9*'Mode d''emploi'!$B$20/60,0) -> 15 | J8: 1 | K8: 10 | L8: non | M8: aucun | N8: Ouverture des hanches, détente du dos et quelques minutes de calme. | O8: Corps : Fente basse (posture du croissant) Corps : Pigeon (version au sol) Corps : Papillon Corps : Bébé heureux Corps : Torsion allongée Corps : Genoux à la poitrine Corps : Respiration lente (6 cycles par minute)
A9: prog_recup_s4 | B9: Récupération : bilan du mois | C9: Jour de programme | F9: 1 | G9: corps_entier | H9: 10 | I9: =ROUND(13.7*'Mode d''emploi'!$B$20/60,0) -> 14 | J9: 1 | K9: 10 | L9: non | M9: aucun | N9: Étirements et scan corporel pour savourer le chemin parcouru. | O9: Corps : Chat-vache Corps : Pince assise Corps : Papillon Corps : Torsion allongée Corps : Méditation : scan corporel
A10: rf_s1_a | B10: Bas du corps et gainage | C10: Jour de programme | F10: 1 | G10: jambes, fessiers, abdos | H10: 11 | I10: =ROUND(22.7*'Mode d''emploi'!$B$20/60,0) -> 23 | J10: 2 | K10: 15 | L10: non | M10: aucun | O10: Échauffement : Marche sur place, genoux hauts Échauffement : Cercles de bras Échauffement : Cercles de hanches Échauffement : Rotations du buste Corps : Squat au poids du corps Corps : Pont fessier Corps : Dead bug Corps : Planche Retour au calme : Étirement des ischio-jambiers
A11: rf_s1_b | B11: Haut du corps et dos | C11: Jour de programme | F11: 1 | G11: bras, epaules, dos | H11: 9 | I11: =ROUND(20*'Mode d''emploi'!$B$20/60,0) -> 20 | J11: 2 | K11: 15 | L11: non | M11: aucun | O11: Échauffement : Marche sur place, genoux hauts Échauffement : Cercles de bras Échauffement : Cercles de hanches Échauffement : Rotations du buste Corps : Pompe sur les genoux Corps : Superman Corps : Bird-dog Corps : Position de l'ours (bear hold) Retour au calme : Posture de l'enfant
A12: rf_s1_c | B12: Cardio doux | C12: Jour de programme | F12: 1 | G12: corps_entier | H12: 8 | I12: =ROUND(24.6*'Mode d''emploi'!$B$20/60,0) -> 25 | J12: 2 | K12: 15 | L12: non | M12: aucun | O12: Échauffement : Cercles de bras Échauffement : Cercles de hanches Corps : Marche sur place, genoux hauts Corps : Jumping jacks sans saut Corps : Squat, coup de pied avant Corps : Boxe dans le vide Retour au calme : Chien tête en bas
A13: rf_s2_a | B13: Bas du corps et gainage | C13: Jour de programme | F13: 1 | G13: jambes, fessiers, abdos | H13: 14 | I13: =ROUND(31.5*'Mode d''emploi'!$B$20/60,0) -> 32 | J13: 2 | K13: 15 | L13: non | M13: aucun | O13: Échauffement : Marche sur place, genoux hauts Échauffement : Cercles de bras Échauffement : Cercles de hanches Échauffement : Rotations du buste Corps : Squat au poids du corps Corps : Fente arrière Corps : Pont fessier Corps : Dead bug Corps : Planche Retour au calme : Étirement des ischio-jambiers Retour au calme : Étirement des fléchisseurs de hanche
A14: rf_s2_b | B14: Haut du corps et dos | C14: Jour de programme | F14: 1 | G14: bras, epaules, dos | H14: 14 | I14: =ROUND(30.1*'Mode d''emploi'!$B$20/60,0) -> 30 | J14: 2 | K14: 15 | L14: non | M14: aucun | O14: Échauffement : Marche sur place, genoux hauts Échauffement : Cercles de bras Échauffement : Cercles de hanches Échauffement : Rotations du buste Corps : Pompe sur les genoux Corps : Superman Corps : Planche, touchers d'épaule Corps : Y, T, W au sol Corps : Bird-dog Corps : Planche inversée Retour au calme : Posture de l'enfant Retour au calme : Étirement de l'épaule, bras croisé
A15: rf_s2_c | B15: Cardio et renforcement | C15: Jour de programme | F15: 1 | G15: corps_entier | H15: 14 | I15: =ROUND(44*'Mode d''emploi'!$B$20/60,0) -> 44 | J15: 2 | K15: 15 | L15: non | M15: aucun | O15: Échauffement : Marche sur place, genoux hauts Échauffement : Cercles de bras Échauffement : Cercles de hanches Corps : Jumping jacks sans saut Corps : Squat au poids du corps Corps : Boxe dans le vide Corps : Mountain climbers lents Corps : Patineur sans saut Corps : Squat, coup de pied avant Retour au calme : Étirement des quadriceps debout Retour au calme : Chien tête en bas
A16: rf_s3_a | B16: Bas du corps et gainage | C16: Jour de programme | F16: 1 | G16: jambes, fessiers, abdos | H16: 20 | I16: =ROUND(45.4*'Mode d''emploi'!$B$20/60,0) -> 45 | J16: 3 | K16: 15 | L16: non | M16: aucun | O16: Échauffement : Marche sur place, genoux hauts Échauffement : Cercles de bras Échauffement : Cercles de hanches Échauffement : Rotations du buste Échauffement : Le plus grand étirement du monde Corps : Squat au poids du corps Corps : Fente arrière Corps : Pont fessier Corps : Dead bug Corps : Planche Retour au calme : Étirement des ischio-jambiers Retour au calme : Étirement des fléchisseurs de hanche
A17: rf_s3_b | B17: Haut du corps et dos | C17: Jour de programme | F17: 1 | G17: bras, epaules, dos | H17: 18 | I17: =ROUND(41.5*'Mode d''emploi'!$B$20/60,0) -> 42 | J17: 3 | K17: 15 | L17: non | M17: aucun | O17: Échauffement : Marche sur place, genoux hauts Échauffement : Cercles de bras Échauffement : Cercles de hanches Échauffement : Rotations du buste Échauffement : Le plus grand étirement du monde Corps : Pompe sur les genoux Corps : Superman Corps : Planche, touchers d'épaule Corps : Y, T, W au sol Corps : Planche inversée Retour au calme : Posture de l'enfant Retour au calme : Étirement de l'épaule, bras croisé
A18: rf_s3_c | B18: Cardio et renforcement | C18: Jour de programme | F18: 1 | G18: corps_entier | H18: 20 | I18: =ROUND(66.3*'Mode d''emploi'!$B$20/60,0) -> 66 | J18: 3 | K18: 15 | L18: non | M18: aucun | O18: Échauffement : Marche sur place, genoux hauts Échauffement : Cercles de bras Échauffement : Cercles de hanches Échauffement : Rotations du buste Corps : Jumping jacks sans saut Corps : Squat au poids du corps Corps : Boxe dans le vide Corps : Mountain climbers lents Corps : Burpee sans saut Corps : Squat, coup de pied avant Retour au calme : Étirement des quadriceps debout Retour au calme : Chien tête en bas
A19: rf_s4_a | B19: Bas du corps et gainage | C19: Jour de programme | F19: 2 | G19: jambes, fessiers, abdos | H19: 24 | I19: =ROUND(54.6*'Mode d''emploi'!$B$20/60,0) -> 55 | J19: 3 | K19: 15 | L19: non | M19: aucun | O19: Échauffement : Marche sur place, genoux hauts Échauffement : Cercles de bras Échauffement : Cercles de hanches Échauffement : Rotations du buste Échauffement : Le plus grand étirement du monde Corps : Squat au poids du corps Corps : Fente arrière Corps : Pont fessier Corps : Fente latérale Corps : Dead bug Corps : Planche Retour au calme : Étirement des ischio-jambiers Retour au calme : Étirement des fléchisseurs de hanche Retour au calme : Étirement des fessiers en « 4 »
A20: rf_s4_b | B20: Haut du corps et dos | C20: Jour de programme | F20: 2 | G20: bras, epaules, dos | H20: 26 | I20: =ROUND(66*'Mode d''emploi'!$B$20/60,0) -> 66 | J20: 3 | K20: 15 | L20: non | M20: aucun | O20: Échauffement : Marche sur place, genoux hauts Échauffement : Cercles de bras Échauffement : Cercles de hanches Échauffement : Rotations du buste Échauffement : Le plus grand étirement du monde Corps : Pompe sur les genoux Corps : Superman Corps : Planche, touchers d'épaule Corps : Y, T, W au sol Corps : Planche inversée Corps : Chenille (inchworm) Corps : Boxe dans le vide Corps : Position de l'ours (bear hold) Retour au calme : Posture de l'enfant Retour au calme : Étirement de l'épaule, bras croisé Retour au calme : Étirement des triceps
A21: rf_s4_c | B21: Cardio et renforcement | C21: Jour de programme | F21: 2 | G21: corps_entier | H21: 23 | I21: =ROUND(76.1*'Mode d''emploi'!$B$20/60,0) -> 76 | J21: 3 | K21: 15 | L21: non | M21: aucun | O21: Échauffement : Marche sur place, genoux hauts Échauffement : Cercles de bras Échauffement : Cercles de hanches Échauffement : Rotations du buste Échauffement : Le plus grand étirement du monde Corps : Jumping jacks sans saut Corps : Squat au poids du corps Corps : Boxe dans le vide Corps : Mountain climbers lents Corps : Burpee sans saut Corps : Patineur sans saut Retour au calme : Étirement des quadriceps debout Retour au calme : Chien tête en bas Retour au calme : Étirement latéral debout
A22: hf_s1_a | B22: Fessiers : les bases | C22: Jour de programme | F22: 1 | G22: fessiers | H22: 12 | I22: =ROUND(27.5*'Mode d''emploi'!$B$20/60,0) -> 28 | J22: 2 | K22: 15 | L22: non | M22: aucun | O22: Échauffement : Marche sur place, genoux hauts Échauffement : Cercles de hanches Échauffement : Balanciers de jambe Échauffement : Squat au poids du corps Corps : Pont fessier Corps : Clamshell (coquillage) Corps : Ruade (donkey kick) Corps : Levée de jambe sur le côté Retour au calme : Étirement des fessiers en « 4 »
A23: hf_s1_b | B23: Jambes et fessiers | C23: Jour de programme | F23: 1 | G23: jambes, fessiers | H23: 11 | I23: =ROUND(23.9*'Mode d''emploi'!$B$20/60,0) -> 24 | J23: 2 | K23: 15 | L23: non | M23: aucun | O23: Échauffement : Marche sur place, genoux hauts Échauffement : Cercles de hanches Échauffement : Balanciers de jambe Échauffement : Squat au poids du corps Corps : Squat sumo Corps : Fente arrière Corps : Bouche d'incendie (fire hydrant) Corps : Montée sur pointes de pieds Retour au calme : Étirement des quadriceps debout
A24: hf_s1_c | B24: Fessiers et abdos | C24: Jour de programme | F24: 1 | G24: fessiers, abdos | H24: 9 | I24: =ROUND(20*'Mode d''emploi'!$B$20/60,0) -> 20 | J24: 2 | K24: 15 | L24: non | M24: aucun | O24: Échauffement : Marche sur place, genoux hauts Échauffement : Cercles de hanches Échauffement : Rotations du buste Corps : Pont fessier en marche Corps : Dead bug Corps : Levée de jambe intérieure (adducteurs) Corps : Crunch inversé Retour au calme : Papillon
A25: hf_s2_a | B25: Fessiers : volume | C25: Jour de programme | F25: 1 | G25: fessiers | H25: 15 | I25: =ROUND(34.9*'Mode d''emploi'!$B$20/60,0) -> 35 | J25: 2 | K25: 15 | L25: non | M25: aucun | O25: Échauffement : Marche sur place, genoux hauts Échauffement : Cercles de hanches Échauffement : Balanciers de jambe Échauffement : Squat au poids du corps Corps : Pont fessier Corps : Hip thrust, épaules sur le canapé Corps : Clamshell (coquillage) Corps : Ruade (donkey kick) Corps : Levée de jambe sur le côté Retour au calme : Étirement des fessiers en « 4 » Retour au calme : Étirement des fléchisseurs de hanche
A26: hf_s2_b | B26: Jambes et fessiers | C26: Jour de programme | F26: 1 | G26: jambes, fessiers | H26: 14 | I26: =ROUND(32.1*'Mode d''emploi'!$B$20/60,0) -> 32 | J26: 2 | K26: 15 | L26: non | M26: aucun | O26: Échauffement : Marche sur place, genoux hauts Échauffement : Cercles de hanches Échauffement : Balanciers de jambe Échauffement : Squat au poids du corps Corps : Squat sumo Corps : Fente arrière Corps : Charnière de hanche (good morning) au poids du corps Corps : Bouche d'incendie (fire hydrant) Corps : Montée sur pointes de pieds Retour au calme : Étirement des quadriceps debout Retour au calme : Étirement des ischio-jambiers
A27: hf_s2_c | B27: Fessiers, abdos et cardio | C27: Jour de programme | F27: 1 | G27: fessiers, abdos | H27: 13 | I27: =ROUND(35*'Mode d''emploi'!$B$20/60,0) -> 35 | J27: 2 | K27: 15 | L27: non | M27: aucun | O27: Échauffement : Marche sur place, genoux hauts Échauffement : Cercles de hanches Échauffement : Rotations du buste Corps : Pont fessier en marche Corps : Patineur sans saut Corps : Dead bug Corps : Levée de jambe intérieure (adducteurs) Corps : Squat, coup de pied avant Retour au calme : Papillon Retour au calme : Étirement des fessiers en « 4 »
A28: hf_s3_a | B28: Fessiers : force | C28: Jour de programme | F28: 1 | G28: fessiers | H28: 21 | I28: =ROUND(47.9*'Mode d''emploi'!$B$20/60,0) -> 48 | J28: 3 | K28: 15 | L28: non | M28: aucun | O28: Échauffement : Marche sur place, genoux hauts Échauffement : Cercles de hanches Échauffement : Balanciers de jambe Échauffement : Squat au poids du corps Corps : Hip thrust, épaules sur le canapé Corps : Pont fessier sur une jambe Corps : Clamshell (coquillage) Corps : Ruade (donkey kick) Corps : Levée de jambe sur le côté Retour au calme : Étirement des fessiers en « 4 » Retour au calme : Étirement des fléchisseurs de hanche
A29: hf_s3_b | B29: Jambes et fessiers | C29: Jour de programme | F29: 1 | G29: jambes, fessiers | H29: 19 | I29: =ROUND(46.7*'Mode d''emploi'!$B$20/60,0) -> 47 | J29: 3 | K29: 15 | L29: non | M29: aucun | O29: Échauffement : Marche sur place, genoux hauts Échauffement : Cercles de hanches Échauffement : Balanciers de jambe Échauffement : Squat au poids du corps Corps : Squat sumo Corps : Fente latérale Corps : Charnière de hanche (good morning) au poids du corps Corps : Fente arrière Corps : Montée sur pointes de pieds Retour au calme : Étirement des quadriceps debout Retour au calme : Étirement des ischio-jambiers
A30: hf_s3_c | B30: Fessiers, abdos et cardio | C30: Jour de programme | F30: 1 | G30: fessiers, abdos | H30: 18 | I30: =ROUND(52.6*'Mode d''emploi'!$B$20/60,0) -> 53 | J30: 3 | K30: 15 | L30: non | M30: aucun | O30: Échauffement : Marche sur place, genoux hauts Échauffement : Cercles de hanches Échauffement : Rotations du buste Échauffement : Balanciers de jambe Corps : Pont fessier en marche Corps : Patineur sans saut Corps : Dead bug Corps : Bouche d'incendie (fire hydrant) Corps : Squat, coup de pied avant Retour au calme : Papillon Retour au calme : Pigeon (version au sol)
A31: hf_s4_a | B31: Fessiers : force | C31: Jour de programme | F31: 2 | G31: fessiers | H31: 25 | I31: =ROUND(57.5*'Mode d''emploi'!$B$20/60,0) -> 58 | J31: 3 | K31: 15 | L31: non | M31: aucun | O31: Échauffement : Marche sur place, genoux hauts Échauffement : Cercles de hanches Échauffement : Balanciers de jambe Échauffement : Squat au poids du corps Corps : Hip thrust, épaules sur le canapé Corps : Pont fessier sur une jambe Corps : Clamshell (coquillage) Corps : Ruade (donkey kick) Corps : Levée de jambe sur le côté Corps : Bouche d'incendie (fire hydrant) Retour au calme : Étirement des fessiers en « 4 » Retour au calme : Étirement des fléchisseurs de hanche Retour au calme : Pigeon (version au sol)
A32: hf_s4_b | B32: Jambes et fessiers | C32: Jour de programme | F32: 2 | G32: jambes, fessiers | H32: 25 | I32: =ROUND(58.1*'Mode d''emploi'!$B$20/60,0) -> 58 | J32: 3 | K32: 15 | L32: non | M32: aucun | O32: Échauffement : Marche sur place, genoux hauts Échauffement : Cercles de hanches Échauffement : Balanciers de jambe Échauffement : Squat au poids du corps Corps : Squat sumo Corps : Fente latérale Corps : Charnière de hanche (good morning) au poids du corps Corps : Fente arrière Corps : Posture de la chaise Corps : Montée sur pointes de pieds Corps : Bouche d'incendie (fire hydrant) Retour au calme : Étirement des quadriceps debout Retour au calme : Étirement des ischio-jambiers Retour au calme : Chien tête en bas
A33: hf_s4_c | B33: Fessiers, abdos et cardio | C33: Jour de programme | F33: 2 | G33: fessiers, abdos | H33: 25 | I33: =ROUND(70*'Mode d''emploi'!$B$20/60,0) -> 70 | J33: 3 | K33: 15 | L33: non | M33: aucun | O33: Échauffement : Marche sur place, genoux hauts Échauffement : Cercles de hanches Échauffement : Rotations du buste Échauffement : Balanciers de jambe Corps : Pont fessier en marche Corps : Patineur sans saut Corps : Dead bug Corps : Bouche d'incendie (fire hydrant) Corps : Squat, coup de pied avant Corps : Levée de jambe intérieure (adducteurs) Corps : Clamshell (coquillage) Retour au calme : Papillon Retour au calme : Pigeon (version au sol) Retour au calme : Bébé heureux
A34: gc_s1_a | B34: Gainage : les bases | C34: Jour de programme | F34: 1 | G34: abdos | H34: 9 | I34: =ROUND(18.2*'Mode d''emploi'!$B$20/60,0) -> 18 | J34: 2 | K34: 15 | L34: non | M34: aucun | O34: Échauffement : Marche sur place, genoux hauts Échauffement : Cercles de bras Échauffement : Cercles de hanches Échauffement : Rotations du buste Corps : Dead bug Corps : Planche Corps : Bird-dog Corps : Planche latérale Retour au calme : Cobra
A35: gc_s1_b | B35: Poussée et tirage au poids du corps | C35: Jour de programme | F35: 1 | G35: bras, dos, epaules | H35: 9 | I35: =ROUND(20.2*'Mode d''emploi'!$B$20/60,0) -> 20 | J35: 2 | K35: 15 | L35: non | M35: aucun | O35: Échauffement : Marche sur place, genoux hauts Échauffement : Cercles de bras Échauffement : Cercles de hanches Échauffement : Rotations du buste Corps : Pompe sur les genoux Corps : Superman Corps : Position de l'ours (bear hold) Corps : Squat au poids du corps Retour au calme : Posture de l'enfant
A36: gc_s1_c | B36: Abdos et rotation | C36: Jour de programme | F36: 1 | G36: abdos | H36: 11 | I36: =ROUND(26.3*'Mode d''emploi'!$B$20/60,0) -> 26 | J36: 2 | K36: 15 | L36: non | M36: aucun | O36: Échauffement : Marche sur place, genoux hauts Échauffement : Rotations du buste Échauffement : Cercles de hanches Corps : Crunch Corps : Touchers de talons Corps : Crunch inversé Corps : Mountain climbers lents Retour au calme : Torsion allongée
A37: gc_s2_a | B37: Gainage : anti-extension | C37: Jour de programme | F37: 1 | G37: abdos | H37: 14 | I37: =ROUND(28.4*'Mode d''emploi'!$B$20/60,0) -> 28 | J37: 2 | K37: 15 | L37: non | M37: aucun | O37: Échauffement : Marche sur place, genoux hauts Échauffement : Cercles de bras Échauffement : Cercles de hanches Échauffement : Rotations du buste Corps : Dead bug Corps : Planche Corps : Hollow hold (position creuse) Corps : Planche latérale Corps : Position de l'ours (bear hold) Corps : Crunch inversé Retour au calme : Cobra Retour au calme : Posture de l'enfant
A38: gc_s2_b | B38: Poussée et tirage au poids du corps | C38: Jour de programme | F38: 1 | G38: bras, dos, epaules | H38: 13 | I38: =ROUND(29.5*'Mode d''emploi'!$B$20/60,0) -> 30 | J38: 2 | K38: 15 | L38: non | M38: aucun | O38: Échauffement : Marche sur place, genoux hauts Échauffement : Cercles de bras Échauffement : Cercles de hanches Échauffement : Rotations du buste Corps : Pompe sur les genoux Corps : Superman Corps : Planche inversée Corps : Y, T, W au sol Corps : Squat au poids du corps Corps : Chenille (inchworm) Retour au calme : Posture de l'enfant Retour au calme : Étirement de l'épaule, bras croisé
A39: gc_s2_c | B39: Abdos et rotation | C39: Jour de programme | F39: 1 | G39: abdos | H39: 13 | I39: =ROUND(30.4*'Mode d''emploi'!$B$20/60,0) -> 30 | J39: 2 | K39: 15 | L39: non | M39: aucun | O39: Échauffement : Marche sur place, genoux hauts Échauffement : Rotations du buste Échauffement : Cercles de hanches Corps : Crunch vélo Corps : Rotation russe Corps : Crunch inversé Corps : Planche, touchers d'épaule Corps : Mountain climbers lents Retour au calme : Torsion allongée Retour au calme : Cobra
A40: gc_s3_a | B40: Gainage : anti-extension | C40: Jour de programme | F40: 1 | G40: abdos | H40: 21 | I40: =ROUND(44.1*'Mode d''emploi'!$B$20/60,0) -> 44 | J40: 3 | K40: 15 | L40: non | M40: aucun | O40: Échauffement : Marche sur place, genoux hauts Échauffement : Cercles de bras Échauffement : Cercles de hanches Échauffement : Rotations du buste Échauffement : Le plus grand étirement du monde Corps : Dead bug Corps : Planche Corps : Hollow hold (position creuse) Corps : Planche latérale Corps : Battements de jambes (ciseaux) Corps : Crunch inversé Corps : Planche, touchers d'épaule Retour au calme : Cobra Retour au calme : Posture de l'enfant
A41: gc_s3_b | B41: Poussée et tirage au poids du corps | C41: Jour de programme | F41: 1 | G41: bras, dos, epaules | H41: 21 | I41: =ROUND(47.5*'Mode d''emploi'!$B$20/60,0) -> 48 | J41: 3 | K41: 15 | L41: non | M41: aucun | O41: Échauffement : Marche sur place, genoux hauts Échauffement : Cercles de bras Échauffement : Cercles de hanches Échauffement : Rotations du buste Échauffement : Le plus grand étirement du monde Corps : Pompe Corps : Superman Corps : Planche inversée Corps : Y, T, W au sol Corps : Chenille (inchworm) Corps : Squat au poids du corps Corps : Planche, touchers d'épaule Retour au calme : Posture de l'enfant Retour au calme : Étirement des triceps
A42: gc_s3_c | B42: Abdos et rotation | C42: Jour de programme | F42: 1 | G42: abdos | H42: 18 | I42: =ROUND(45.1*'Mode d''emploi'!$B$20/60,0) -> 45 | J42: 3 | K42: 15 | L42: non | M42: aucun | O42: Échauffement : Marche sur place, genoux hauts Échauffement : Rotations du buste Échauffement : Cercles de hanches Échauffement : Cercles de bras Corps : Crunch vélo Corps : Rotation russe Corps : Relevé de jambes Corps : Planche montante (coudes, puis mains) Corps : Mountain climbers lents Retour au calme : Torsion allongée Retour au calme : Cobra
A43: gc_s4_a | B43: Gainage : anti-extension | C43: Jour de programme | F43: 2 | G43: abdos | H43: 24 | I43: =ROUND(50.3*'Mode d''emploi'!$B$20/60,0) -> 50 | J43: 3 | K43: 15 | L43: non | M43: aucun | O43: Échauffement : Marche sur place, genoux hauts Échauffement : Cercles de bras Échauffement : Cercles de hanches Échauffement : Rotations du buste Échauffement : Le plus grand étirement du monde Corps : Dead bug Corps : Planche Corps : Hollow hold (position creuse) Corps : Planche latérale Corps : Battements de jambes (ciseaux) Corps : Position de l'ours (bear hold) Corps : Relevé de jambes Corps : Planche latérale avec rotation Retour au calme : Cobra Retour au calme : Posture de l'enfant Retour au calme : Genoux à la poitrine
A44: gc_s4_b | B44: Poussée et tirage au poids du corps | C44: Jour de programme | F44: 2 | G44: bras, dos, epaules | H44: 24 | I44: =ROUND(54.8*'Mode d''emploi'!$B$20/60,0) -> 55 | J44: 3 | K44: 15 | L44: non | M44: aucun | O44: Échauffement : Marche sur place, genoux hauts Échauffement : Cercles de bras Échauffement : Cercles de hanches Échauffement : Rotations du buste Échauffement : Le plus grand étirement du monde Corps : Pompe Corps : Superman Corps : Planche inversée Corps : Pompe en V (pike push-up) Corps : Y, T, W au sol Corps : Chenille (inchworm) Corps : Squat au poids du corps Corps : Position de l'ours (bear hold) Retour au calme : Posture de l'enfant Retour au calme : Étirement des triceps Retour au calme : Étirement de l'épaule, bras croisé
A45: gc_s4_c | B45: Abdos et rotation | C45: Jour de programme | F45: 2 | G45: abdos | H45: 23 | I45: =ROUND(56.8*'Mode d''emploi'!$B$20/60,0) -> 57 | J45: 3 | K45: 15 | L45: non | M45: aucun | O45: Échauffement : Marche sur place, genoux hauts Échauffement : Rotations du buste Échauffement : Cercles de hanches Échauffement : Cercles de bras Échauffement : Chat-vache Corps : Crunch vélo Corps : Rotation russe Corps : Relevé de jambes Corps : Planche montante (coudes, puis mains) Corps : Planche latérale avec rotation Corps : Mountain climbers lents Retour au calme : Torsion allongée Retour au calme : Cobra Retour au calme : Genoux à la poitrine
A46: rapide_corps_entier_1 | B46: Corps entier, débutant | C46: Démarrage rapide | F46: 1 | G46: corps_entier | H46: 8 | I46: =ROUND(17.2*'Mode d''emploi'!$B$20/60,0) -> 17 | J46: 2 | K46: 15 | L46: non | M46: aucun | O46: Échauffement : Marche sur place, genoux hauts Échauffement : Cercles de bras Corps : Squat au poids du corps Corps : Pompe sur les genoux Corps : Pont fessier Corps : Planche Retour au calme : Posture de l'enfant
A47: rapide_corps_entier_2 | B47: Corps entier, intermédiaire | C47: Démarrage rapide | F47: 2 | G47: corps_entier | H47: 13 | I47: =ROUND(32.9*'Mode d''emploi'!$B$20/60,0) -> 33 | J47: 2 | K47: 15 | L47: non | M47: aucun | O47: Échauffement : Marche sur place, genoux hauts Échauffement : Cercles de bras Échauffement : Cercles de hanches Échauffement : Rotations du buste Corps : Squat au poids du corps Corps : Pompe sur les genoux Corps : Fente arrière Corps : Mountain climbers lents Corps : Superman Retour au calme : Posture de l'enfant Retour au calme : Étirement des quadriceps debout
A48: rapide_corps_entier_3 | B48: Corps entier, avancé | C48: Démarrage rapide | F48: 3 | G48: corps_entier | H48: 17 | I48: =ROUND(66.7*'Mode d''emploi'!$B$20/60,0) -> 67 | J48: 3 | K48: 15 | L48: oui | M48: aucun | O48: Échauffement : Marche sur place, genoux hauts Échauffement : Cercles de bras Échauffement : Cercles de hanches Échauffement : Rotations du buste Corps : Squat sauté Corps : Pompe Corps : Fente arrière Corps : Burpee Corps : Planche montante (coudes, puis mains) Corps : Jumping jacks Retour au calme : Posture de l'enfant Retour au calme : Étirement des quadriceps debout
A49: rapide_abdos_1 | B49: Abdos, débutant | C49: Démarrage rapide | F49: 1 | G49: abdos | H49: 8 | I49: =ROUND(15.7*'Mode d''emploi'!$B$20/60,0) -> 16 | J49: 2 | K49: 15 | L49: non | M49: aucun | O49: Échauffement : Rotations du buste Échauffement : Cercles de hanches Corps : Dead bug Corps : Crunch Corps : Planche Corps : Crunch inversé Retour au calme : Cobra
A50: rapide_abdos_2 | B50: Abdos, intermédiaire | C50: Démarrage rapide | F50: 2 | G50: abdos | H50: 13 | I50: =ROUND(27.2*'Mode d''emploi'!$B$20/60,0) -> 27 | J50: 2 | K50: 15 | L50: non | M50: aucun | O50: Échauffement : Marche sur place, genoux hauts Échauffement : Rotations du buste Échauffement : Cercles de hanches Corps : Crunch vélo Corps : Planche Corps : Rotation russe Corps : Battements de jambes (ciseaux) Corps : Planche latérale Retour au calme : Cobra Retour au calme : Torsion allongée
A51: rapide_abdos_3 | B51: Abdos, avancé | C51: Démarrage rapide | F51: 3 | G51: abdos | H51: 18 | I51: =ROUND(57*'Mode d''emploi'!$B$20/60,0) -> 57 | J51: 3 | K51: 15 | L51: oui | M51: aucun | O51: Échauffement : Marche sur place, genoux hauts Échauffement : Rotations du buste Échauffement : Cercles de hanches Corps : Hollow hold (position creuse) Corps : V-up (relevé en V) Corps : Planche montante (coudes, puis mains) Corps : Rotation russe Corps : Relevé de jambes Corps : Mountain climbers Retour au calme : Cobra Retour au calme : Torsion allongée
A52: rapide_jambes_1 | B52: Jambes, débutant | C52: Démarrage rapide | F52: 1 | G52: jambes | H52: 9 | I52: =ROUND(21.1*'Mode d''emploi'!$B$20/60,0) -> 21 | J52: 2 | K52: 15 | L52: non | M52: aucun | O52: Échauffement : Marche sur place, genoux hauts Échauffement : Cercles de hanches Corps : Squat au poids du corps Corps : Fente arrière Corps : Montée sur pointes de pieds Corps : Pont fessier Retour au calme : Étirement des quadriceps debout
A53: rapide_jambes_2 | B53: Jambes, intermédiaire | C53: Démarrage rapide | F53: 2 | G53: jambes | H53: 14 | I53: =ROUND(32.1*'Mode d''emploi'!$B$20/60,0) -> 32 | J53: 2 | K53: 15 | L53: non | M53: aucun | O53: Échauffement : Marche sur place, genoux hauts Échauffement : Cercles de hanches Échauffement : Balanciers de jambe Échauffement : Squat au poids du corps Corps : Squat sumo Corps : Fente latérale Corps : Charnière de hanche (good morning) au poids du corps Corps : Pont fessier sur une jambe Corps : Montée sur pointes de pieds Retour au calme : Étirement des quadriceps debout Retour au calme : Étirement des ischio-jambiers
A54: rapide_jambes_3 | B54: Jambes, avancé | C54: Démarrage rapide | F54: 3 | G54: jambes | H54: 18 | I54: =ROUND(66.6*'Mode d''emploi'!$B$20/60,0) -> 67 | J54: 3 | K54: 15 | L54: oui | M54: aucun | O54: Échauffement : Marche sur place, genoux hauts Échauffement : Cercles de hanches Échauffement : Balanciers de jambe Échauffement : Squat au poids du corps Corps : Squat sauté Corps : Fente arrière Corps : Fente latérale Corps : Pont fessier sur une jambe Corps : Patineur sauté Retour au calme : Étirement des quadriceps debout Retour au calme : Étirement des ischio-jambiers
A55: rapide_bras_1 | B55: Bras, débutant | C55: Démarrage rapide | F55: 1 | G55: bras | H55: 8 | I55: =ROUND(19.2*'Mode d''emploi'!$B$20/60,0) -> 19 | J55: 2 | K55: 15 | L55: non | M55: aucun | O55: Échauffement : Cercles de bras Échauffement : Marche sur place, genoux hauts Corps : Pompe sur les genoux Corps : Planche inversée Corps : Boxe dans le vide Corps : Position de l'ours (bear hold) Retour au calme : Étirement des triceps
A56: rapide_bras_2 | B56: Bras, intermédiaire | C56: Démarrage rapide | F56: 2 | G56: bras | H56: 12 | I56: =ROUND(32.2*'Mode d''emploi'!$B$20/60,0) -> 32 | J56: 2 | K56: 15 | L56: non | M56: aucun | O56: Échauffement : Cercles de bras Échauffement : Marche sur place, genoux hauts Échauffement : Rotations du buste Corps : Pompe sur les genoux Corps : Planche inversée Corps : Boxe dans le vide Corps : Pompe Corps : Planche montante (coudes, puis mains) Corps : Position de l'ours (bear hold) Retour au calme : Étirement des triceps Retour au calme : Étirement de l'épaule, bras croisé
A57: rapide_bras_3 | B57: Bras, avancé | C57: Démarrage rapide | F57: 3 | G57: bras | H57: 18 | I57: =ROUND(48.8*'Mode d''emploi'!$B$20/60,0) -> 49 | J57: 3 | K57: 15 | L57: non | M57: aucun | O57: Échauffement : Cercles de bras Échauffement : Marche sur place, genoux hauts Échauffement : Rotations du buste Corps : Pompe Corps : Pompe mains serrées (triceps) Corps : Planche inversée Corps : Pompe en V (pike push-up) Corps : Planche montante (coudes, puis mains) Corps : Boxe dans le vide Retour au calme : Étirement des triceps Retour au calme : Étirement de l'épaule, bras croisé
A58: rapide_epaules_1 | B58: Épaules, débutant | C58: Démarrage rapide | F58: 1 | G58: epaules | H58: 7 | I58: =ROUND(17.2*'Mode d''emploi'!$B$20/60,0) -> 17 | J58: 2 | K58: 15 | L58: non | M58: aucun | O58: Échauffement : Cercles de bras Échauffement : Rotations du buste Corps : Y, T, W au sol Corps : Position de l'ours (bear hold) Corps : Boxe dans le vide Corps : Planche Retour au calme : Étirement de l'épaule, bras croisé
A59: rapide_epaules_2 | B59: Épaules, intermédiaire | C59: Démarrage rapide | F59: 2 | G59: epaules | H59: 12 | I59: =ROUND(32.2*'Mode d''emploi'!$B$20/60,0) -> 32 | J59: 2 | K59: 15 | L59: non | M59: aucun | O59: Échauffement : Cercles de bras Échauffement : Marche sur place, genoux hauts Échauffement : Rotations du buste Corps : Y, T, W au sol Corps : Planche, touchers d'épaule Corps : Pompe sur les genoux Corps : Boxe dans le vide Corps : Position de l'ours (bear hold) Retour au calme : Étirement de l'épaule, bras croisé Retour au calme : Chien tête en bas
A60: rapide_epaules_3 | B60: Épaules, avancé | C60: Démarrage rapide | F60: 3 | G60: epaules | H60: 19 | I60: =ROUND(58.9*'Mode d''emploi'!$B$20/60,0) -> 59 | J60: 3 | K60: 15 | L60: non | M60: aucun | O60: Échauffement : Cercles de bras Échauffement : Marche sur place, genoux hauts Échauffement : Rotations du buste Corps : Pompe en V (pike push-up) Corps : Y, T, W au sol Corps : Planche, touchers d'épaule Corps : Marche de l'ours Corps : Pompe Corps : Boxe dans le vide Retour au calme : Étirement de l'épaule, bras croisé Retour au calme : Chien tête en bas
A61: rapide_dos_1 | B61: Dos, débutant | C61: Démarrage rapide | F61: 1 | G61: dos | H61: 8 | I61: =ROUND(17.8*'Mode d''emploi'!$B$20/60,0) -> 18 | J61: 2 | K61: 15 | L61: non | M61: aucun | O61: Échauffement : Chat-vache Échauffement : Cercles de bras Corps : Bird-dog Corps : Superman Corps : Pont fessier Corps : Y, T, W au sol Retour au calme : Posture de l'enfant
A62: rapide_dos_2 | B62: Dos, intermédiaire | C62: Démarrage rapide | F62: 2 | G62: dos | H62: 12 | I62: =ROUND(24.7*'Mode d''emploi'!$B$20/60,0) -> 25 | J62: 2 | K62: 15 | L62: non | M62: aucun | O62: Échauffement : Chat-vache Échauffement : Cercles de bras Échauffement : Rotations du buste Corps : Superman Corps : Y, T, W au sol Corps : Bird-dog Corps : Charnière de hanche (good morning) au poids du corps Corps : Planche inversée Retour au calme : Posture de l'enfant Retour au calme : Sphinx
A63: rapide_dos_3 | B63: Dos, avancé | C63: Démarrage rapide | F63: 3 | G63: dos | H63: 19 | I63: =ROUND(41.8*'Mode d''emploi'!$B$20/60,0) -> 42 | J63: 3 | K63: 15 | L63: non | M63: aucun | O63: Échauffement : Chat-vache Échauffement : Cercles de bras Échauffement : Rotations du buste Échauffement : Le plus grand étirement du monde Corps : Superman Corps : Y, T, W au sol Corps : Planche inversée Corps : Charnière de hanche (good morning) au poids du corps Corps : Chenille (inchworm) Corps : Bird-dog Retour au calme : Posture de l'enfant Retour au calme : Sphinx
A64: decouverte_yoga_matin | B64: Yoga du matin | C64: Découverte | F64: 1 | G64: corps_entier | H64: 8 | I64: =ROUND(17.4*'Mode d''emploi'!$B$20/60,0) -> 17 | J64: 1 | K64: 5 | L64: non | M64: aucun | N64: Une séquence douce pour réveiller le corps : salutation au soleil et postures debout. | O64: Corps : Posture de la montagne Corps : Chat-vache Corps : Salutation au soleil (version douce) Corps : Posture de la chaise Corps : Guerrier I Corps : Guerrier II Corps : Triangle Corps : Arbre Corps : Posture de l'enfant
A65: decouverte_etirements_soir | B65: Étirements du soir | C65: Découverte | F65: 1 | G65: corps_entier | H65: 9 | I65: =ROUND(16.6*'Mode d''emploi'!$B$20/60,0) -> 17 | J65: 1 | K65: 5 | L65: non | M65: aucun | N65: Relâcher les tensions de la journée avant de dormir, tout en douceur. | O65: Corps : Étirement latéral debout Corps : Étirement des quadriceps debout Corps : Sphinx Corps : Genoux à la poitrine Corps : Étirement des fessiers en « 4 » Corps : Étirement des ischio-jambiers Corps : Torsion allongée Corps : Papillon Corps : Respiration costale
A66: decouverte_meditation | B66: Méditation guidée | C66: Découverte | F66: 1 | H66: 8 | I66: =ROUND(7.1*'Mode d''emploi'!$B$20/60,0) -> 7 | J66: 1 | K66: 5 | L66: non | M66: aucun | N66: Quelques minutes de respiration lente, puis d'attention au souffle. | O66: Corps : Respiration lente (6 cycles par minute) Corps : Méditation : attention au souffle
A67: decouverte_gainage_express | B67: Gainage express | C67: Découverte | F67: 1 | G67: abdos | H67: 5 | I67: =ROUND(11.4*'Mode d''emploi'!$B$20/60,0) -> 11 | J67: 2 | K67: 10 | L67: non | M67: aucun | N67: Un gainage court et efficace, quand il ne reste que quelques minutes. | O67: Corps : Planche Corps : Dead bug Corps : Planche latérale Corps : Bird-dog
A68: decouverte_detente_sommeil | B68: Détente avant le sommeil | C68: Découverte | F68: 1 | H68: 12 | I68: =ROUND(13.8*'Mode d''emploi'!$B$20/60,0) -> 14 | J68: 1 | K68: 5 | L68: non | M68: mur | N68: Jambes au mur, puis relaxation progressive pour préparer le sommeil. | O68: Corps : Jambes contre le mur Corps : Relaxation musculaire progressive Corps : Respiration lente (6 cycles par minute)
A69: decouverte_yoga_hanches | B69: Yoga des hanches | C69: Découverte | F69: 1 | G69: fessiers, jambes | H69: 8 | I69: =ROUND(16.7*'Mode d''emploi'!$B$20/60,0) -> 17 | J69: 1 | K69: 5 | L69: non | M69: aucun | N69: Ouvrir les hanches après une journée assise. | O69: Corps : Chat-vache Corps : Fente basse (posture du croissant) Corps : Guerrier II Corps : Pigeon (version au sol) Corps : Papillon Corps : Pince assise Corps : Bébé heureux Corps : Torsion allongée
A70: decouverte_scan_corporel | B70: Scan corporel | C70: Découverte | F70: 1 | H70: 9 | I70: =ROUND(8.1*'Mode d''emploi'!$B$20/60,0) -> 8 | J70: 1 | K70: 5 | L70: non | M70: aucun | N70: Parcourir le corps de la tête aux pieds pour se poser. | O70: Corps : Respiration costale Corps : Méditation : scan corporel
A71: express_reveil | B71: Réveil en 4 minutes | C71: Express (hors ligne) | F71: 1 | G71: corps_entier | H71: 3 | I71: =ROUND(6.7*'Mode d''emploi'!$B$20/60,0) -> 7 | J71: 1 | K71: 5 | L71: non | M71: aucun | N71: Mobilité du matin, sans quitter la chambre. | O71: Corps : Cercles de bras Corps : Rotations du buste Corps : Cercles de hanches Corps : Chat-vache Corps : Squat au poids du corps
A72: express_cardio | B72: Coup de boost cardio | C72: Express (hors ligne) | F72: 1 | G72: corps_entier | H72: 4 | I72: =ROUND(13.8*'Mode d''emploi'!$B$20/60,0) -> 14 | J72: 2 | K72: 10 | L72: non | M72: aucun | N72: Quatre minutes pour se réchauffer, sans saut. | O72: Corps : Jumping jacks sans saut Corps : Boxe dans le vide Corps : Marche sur place, genoux hauts
A73: express_abdos | B73: Abdos express | C73: Express (hors ligne) | F73: 1 | G73: abdos | H73: 5 | I73: =ROUND(10.5*'Mode d''emploi'!$B$20/60,0) -> 11 | J73: 2 | K73: 10 | L73: non | M73: aucun | N73: Quatre exercices de gainage enchaînés deux fois. | O73: Corps : Planche Corps : Dead bug Corps : Crunch Corps : Planche latérale
A74: express_jambes | B74: Jambes express | C74: Express (hors ligne) | F74: 1 | G74: jambes, fessiers | H74: 5 | I74: =ROUND(11.8*'Mode d''emploi'!$B$20/60,0) -> 12 | J74: 2 | K74: 10 | L74: non | M74: aucun | N74: Squats, fentes et pont : l'essentiel des jambes. | O74: Corps : Squat au poids du corps Corps : Fente arrière Corps : Pont fessier Corps : Montée sur pointes de pieds
A75: express_pause_bureau | B75: Pause bureau | C75: Express (hors ligne) | F75: 1 | G75: dos, epaules | H75: 4 | I75: =ROUND(8.9*'Mode d''emploi'!$B$20/60,0) -> 9 | J75: 1 | K75: 5 | L75: non | M75: aucun | N75: Dénouer la nuque, les épaules et le dos entre deux réunions. | O75: Corps : Menton rentré Corps : Rapprochement des omoplates Corps : Étirement des trapèzes Corps : Étirement de l'épaule, bras croisé Corps : Étirement latéral debout
A76: express_respiration | B76: Trois minutes pour respirer | C76: Express (hors ligne) | F76: 1 | H76: 3 | I76: =ROUND(3*'Mode d''emploi'!$B$20/60,0) -> 3 | J76: 1 | K76: 0 | L76: non | M76: aucun | N76: Respiration lente pour faire redescendre la pression. | O76: Corps : Respiration lente (6 cycles par minute)

Sheet Programmes
A1: Programme | B1: Jour | C1: Semaine | D1: Entraînement | E1: Titre | F1: Durée (min)
A2: Remise en forme | B2: 1 | C2: 1 | D2: rf_s1_a | E2: Bas du corps et gainage | F2: 11
A3: Remise en forme | B3: 2 | C3: 1 | D3: rf_s1_b | E3: Haut du corps et dos | F3: 9
A4: Remise en forme | B4: 3 | C4: 1 | D4: prog_mobilite_s1 | E4: Mobilité douce | F4: 5
A5: Remise en forme | B5: 4 | C5: 1 | D5: rf_s1_c | E5: Cardio doux | F5: 8
A6: Remise en forme | B6: 5 | C6: 1 | D6: rf_s1_a | E6: Bas du corps et gainage | F6: 11
A7: Remise en forme | B7: 6 | C7: 1 | D7: rf_s1_b | E7: Haut du corps et dos | F7: 9
A8: Remise en forme | B8: 7 | C8: 1 | D8: prog_recup_s1 | E8: Récupération : étirements | F8: 7
A9: Remise en forme | B9: 8 | C9: 2 | D9: rf_s2_a | E9: Bas du corps et gainage | F9: 14
A10: Remise en forme | B10: 9 | C10: 2 | D10: rf_s2_b | E10: Haut du corps et dos | F10: 14
A11: Remise en forme | B11: 10 | C11: 2 | D11: prog_mobilite_s2 | E11: Mobilité du dos et des hanches | F11: 6
A12: Remise en forme | B12: 11 | C12: 2 | D12: rf_s2_c | E12: Cardio et renforcement | F12: 14
A13: Remise en forme | B13: 12 | C13: 2 | D13: rf_s2_a | E13: Bas du corps et gainage | F13: 14
... A85: Gainage et calisthénie | B85: 28 | C85: 4 | D85: prog_recup_s4 | E85: Récupération : bilan du mois | F85: 10
A87: Programme | B87: Validé | C87: Commentaire | D87: Description
A88: Remise en forme | D88: 28 jours pour retrouver la forme : bas du corps, haut du corps et cardio doux en alternance, sans matériel et sans saut. Les séances passent de 10 à 25 minutes au fil des semaines.
A89: Hanches et fessiers | D89: 28 jours pour tonifier les fessiers et les jambes : ponts, fentes, travail de hanche et un peu de cardio, sans matériel et sans saut. De 10 à 25 minutes par séance.
A90: Gainage et calisthénie | D90: 28 jours pour un tronc solide et les bases de la calisthénie : planches, dead bug, pompes et travail du dos au poids du corps. De 10 à 25 minutes par séance.
